Workbook
Name TABATUAL: [1]Plan2!$A$1:$B$1285

Sheet COMMERCIAL INVOICE
A1: #VALUE! | C1: COMMERCIAL INVOICE | Q1: C-129/2026
A4: Exporter and Manufacturer | Q4: Date: | R4: 06/24/2026
A5: LIVE ROUPAS ESPORTIVAS LTDA | Q5: Place of Loading: | R5: Place of Delivery:
A6: RUA MANOEL FRANCISCO DA COSTA, 1600, PREDIO 01, PISO 02 | Q6: Jaraguá do Sul/BR | R6: Miami/USA
A7: VIEIRA - JARAGUÁ DO SUL - SANTA CATARINA - BRASIL | Q7: Total Net Weight: | R7: Total Gross Weight:
A8: CNPJ: 05.108.435/0001-78 | Q8: 34.32 | R8: 38.4
A9: TEL.: 55 47 2106 7400 | Q9: Country of Origin: | R9: Volumes:
Q10: Brazil | R10: 3 Cartoon Boxes
A11: BUYER
A12: CUSTOMER: | D12: LIVE! CLOTHING LLC - EIN 371775533
A13: CONTACT PERSON: | D13: CINTIA NETTO
A14: ADDRESS: | D14: 723 LINCOLN ROAD - 33139
A15: CITY: | D15: MIAMI - FL
A16: COUNTRY: | D16: UNITED STATES OF AMERICA
A17: EMAIL: | D17: ecommerce@liveclothing.com
A18: PHONE: | D18: +1 (305) 537-4910 / (561) 543-5998
A19: SHIP TO
A20: CONSIGNEE: | D20: LIVE! CLOTHING LLC - EIN 371775533
A21: CONTACT PERSON: | D21: CINTIA NETTO
A22: ADDRESS: | D22: 723 LINCOLN ROAD - 33139
A23: CITY: | D23: MIAMI - FL
A24: COUNTRY: | D24: UNITED STATES OF AMERICA
A25: EMAIL: | D25: ecommerce@liveclothing.com
A26: PHONE: | D26: +1 (305) 537-4910 / (561) 543-5998
A27: INCOTERM: | D27: CIP
A28: TERMS OF PAYMENT: | D28: 365 DAYS AFTER INVOICE DATE
A29: REFERENCE | B29: NCM | C29: COLOR | D29: PRODUCT MATERIALS | E29: GENERAL DESCRIPTION | F29: COMPOSITION | J29: DESCRIPTION | K29: XS | L29: S | M29: M | N29: L | O29: XL | P29: UNIT | Q29: UNIT PRICE USD | R29: TOTAL AMOUNT USD
A30: 46586 | B30: 6114.30.30.30 | C30: 00RX80 | D30: Of man-made fibres | E30: Activewear Clothes, Knit. | F30: =VLOOKUP(A30,'[2]Todas Coleções'!$A:$E,5,FALSE) -> 92% PA / 8% EL | G30: =_xlfn.IMAGE(H30) -> #VALUE! | H30: =VLOOKUP(I30,[3]exportarImagens_10_07_2026_09_4!$C:$D,2,FALSE) -> https://imagens.liveoficial.com.br/product/80x120/506971_46586_00RX80_1.jpg | I30: =A30&C30 -> 4658600RX80 | J30: Melt Square Bra | M30: 3 | N30: 2 | P30: =SUM(K30:O30) -> 5 | Q30: =VLOOKUP(A30,'SOLVER NOVO'!A:E,5,FALSE) -> 8.6141795 | R30: =Q30*P30 -> 43.070897
A31: 46588 | B31: 6104.63.10.20 | C31: 00RX80 | D31: Of synthetic fibres | E31: Activewear Clothes, Knit. | F31: =VLOOKUP(A31,'[2]Todas Coleções'!$A:$E,5,FALSE) -> 92% PA / 8% EL | G31: =_xlfn.IMAGE(H31) -> #VALUE! | H31: =VLOOKUP(I31,[3]exportarImagens_10_07_2026_09_4!$C:$D,2,FALSE) -> https://imagens.liveoficial.com.br/product/80x120/506979_46588_00RX80_1.jpg | I31: =A31&C31 -> 4658800RX80 | J31: Melt Square Full Legging | M31: 2 | P31: =SUM(K31:O31) -> 2 | Q31: =VLOOKUP(A31,'SOLVER NOVO'!A:E,5,FALSE) -> 10.493706 | R31: =Q31*P31 -> 20.987412
A32: 46589 | B32: 6104.63.10.20 | C32: 00RX80 | D32: Of synthetic fibres | E32: Activewear Clothes, Knit. | F32: =VLOOKUP(A32,'[2]Todas Coleções'!$A:$E,5,FALSE) -> 92% PA / 8% EL | G32: =_xlfn.IMAGE(H32) -> #VALUE! | H32: =VLOOKUP(I32,[3]exportarImagens_10_07_2026_09_4!$C:$D,2,FALSE) -> https://imagens.liveoficial.com.br/product/80x120/501029_46589_00RX80_1.jpg | I32: =A32&C32 -> 4658900RX80 | J32: Square Melt Ballerina Pants | L32: 2 | P32: =SUM(K32:O32) -> 2 | Q32: =VLOOKUP(A32,'SOLVER NOVO'!A:E,5,FALSE) -> 9.0113994 | R32: =Q32*P32 -> 18.022799
A33: 46591 | B33: 6104.63.10.20 | C33: 00RX80 | D33: Of synthetic fibres | E33: Activewear Clothes, Knit. | F33: =VLOOKUP(A33,'[2]Todas Coleções'!$A:$E,5,FALSE) -> 97% PA / 3% EL | G33: =_xlfn.IMAGE(H33) -> #VALUE! | H33: =VLOOKUP(I33,[3]exportarImagens_10_07_2026_09_4!$C:$D,2,FALSE) -> https://imagens.liveoficial.com.br/product/80x120/501021_46591_00RX80_1.jpg | I33: =A33&C33 -> 4659100RX80 | J33: Seamless Mesh Full Legging | L33: 2 | M33: 2 | P33: =SUM(K33:O33) -> 4 | Q33: =VLOOKUP(A33,'SOLVER NOVO'!A:E,5,FALSE) -> 9.6712217 | R33: =Q33*P33 -> 38.684887
A34: 46592 | B34: 6114.30.30.30 | C34: 00RX80 | D34: Of man-made fibres | E34: Activewear Clothes, Knit. | F34: =VLOOKUP(A34,'[2]Todas Coleções'!$A:$E,5,FALSE) -> 97% PA / 3% EL | G34: =_xlfn.IMAGE(H34) -> #VALUE! | H34: =VLOOKUP(I34,[3]exportarImagens_10_07_2026_09_4!$C:$D,2,FALSE) -> https://imagens.liveoficial.com.br/product/80x120/500982_46592_00RX80_1.jpg | I34: =A34&C34 -> 4659200RX80 | J34: Seamless Knit Short Bodysuit | K34: 1 | L34: 3 | P34: =SUM(K34:O34) -> 4 | Q34: =VLOOKUP(A34,'SOLVER NOVO'!A:E,5,FALSE) -> 9.764121 | R34: =Q34*P34 -> 39.056484
A35: P0063 | B35: 6114.30.30.30 | C35: 00BC14 | D35: Of man-made fibres | E35: Activewear Clothes, Knit. | F35: =VLOOKUP(A35,'[2]Todas Coleções'!$A:$E,5,FALSE) -> 87% PA / 13% EL | G35: =_xlfn.IMAGE(H35) -> #VALUE! | H35: =VLOOKUP(I35,[3]exportarImagens_10_07_2026_09_4!$C:$D,2,FALSE) -> https://imagens.liveoficial.com.br/product/80x120/515440_P0063_00BC14_2.jpg | I35: =A35&C35 -> P006300BC14 | J35: LIVE Curve Bra | K35: 1 | L35: 3 | O35: 1 | P35: =SUM(K35:O35) -> 5 | Q35: =VLOOKUP(A35,'SOLVER NOVO'!A:E,5,FALSE) -> 11.37848 | R35: =Q35*P35 -> 56.8924
A36: P1153 | B36: 6109.90.80.10 | C36: 00BC14 | D36: Of other textile materials | E36: Activewear Clothes, Knit. | F36: =VLOOKUP(A36,'[2]Todas Coleções'!$A:$E,5,FALSE) -> 100% PA | G36: =_xlfn.IMAGE(H36) -> #VALUE! | H36: =VLOOKUP(I36,[3]exportarImagens_10_07_2026_09_4!$C:$D,2,FALSE) -> https://imagens.liveoficial.com.br/product/80x120/515554_P1153_00BC14_1.jpg | I36: =A36&C36 -> P115300BC14 | J36: LIVE Comfort TShirt | K36: 1 | L36: 3 | M36: 3 | N36: 1 | O36: 1 | P36: =SUM(K36:O36) -> 9 | Q36: =VLOOKUP(A36,'SOLVER NOVO'!A:E,5,FALSE) -> 9.1533296 | R36: =Q36*P36 -> 82.379967
A37: P1153 | B37: 6109.90.80.10 | C37: 00RX80 | D37: Of other textile materials | E37: Activewear Clothes, Knit. | F37: =VLOOKUP(A37,'[2]Todas Coleções'!$A:$E,5,FALSE) -> 100% PA | G37: =_xlfn.IMAGE(H37) -> #VALUE! | H37: =VLOOKUP(I37,[3]exportarImagens_10_07_2026_09_4!$C:$D,2,FALSE) -> https://imagens.liveoficial.com.br/product/80x120/522333_P1153_00RX80_1.jpg | I37: =A37&C37 -> P115300RX80 | J37: LIVE Comfort TShirt | L37: 3 | N37: 2 | P37: =SUM(K37:O37) -> 5 | Q37: =VLOOKUP(A37,'SOLVER NOVO'!A:E,5,FALSE) -> 9.1533296 | R37: =Q37*P37 -> 45.766648
A38: P1153 | B38: 6109.90.80.10 | C38: 0AZ190 | D38: Of other textile materials | E38: Activewear Clothes, Knit. | F38: =VLOOKUP(A38,'[2]Todas Coleções'!$A:$E,5,FALSE) -> 100% PA | G38: =_xlfn.IMAGE(H38) -> #VALUE! | H38: =VLOOKUP(I38,[3]exportarImagens_10_07_2026_09_4!$C:$D,2,FALSE) -> https://imagens.liveoficial.com.br/product/80x120/521961_P1153_0AZ190_2.jpg | I38: =A38&C38 -> P11530AZ190 | J38: LIVE Comfort TShirt | K38: 1 | L38: 2 | N38: 1 | P38: =SUM(K38:O38) -> 4 | Q38: =VLOOKUP(A38,'SOLVER NOVO'!A:E,5,FALSE) -> 9.1533296 | R38: =Q38*P38 -> 36.613319
A39: P1154 | B39: 6106.20.10.10 | C39: 00BC14 | D39: Of man-made fibres | E39: Activewear Clothes, Knit. | F39: =VLOOKUP(A39,'[2]Todas Coleções'!$A:$E,5,FALSE) -> 100% PA | G39: =_xlfn.IMAGE(H39) -> #VALUE! | H39: =VLOOKUP(I39,[3]exportarImagens_10_07_2026_09_4!$C:$D,2,FALSE) -> https://imagens.liveoficial.com.br/product/80x120/515472_P1154_00BC14_2.jpg | I39: =A39&C39 -> P115400BC14 | J39: LIVE Comfort Tank Top | L39: 3 | P39: =SUM(K39:O39) -> 3 | Q39: =VLOOKUP(A39,'SOLVER NOVO'!A:E,5,FALSE) -> 7.817765 | R39: =Q39*P39 -> 23.453295
A40: P1154 | B40: 6106.20.10.10 | C40: 00RX80 | D40: Of man-made fibres | E40: Activewear Clothes, Knit. | F40: =VLOOKUP(A40,'[2]Todas Coleções'!$A:$E,5,FALSE) -> 100% PA | G40: =_xlfn.IMAGE(H40) -> #VALUE! | H40: =VLOOKUP(I40,[3]exportarImagens_10_07_2026_09_4!$C:$D,2,FALSE) -> https://imagens.liveoficial.com.br/product/80x120/508191_P1154_00RX80_2.jpg | I40: =A40&C40 -> P115400RX80 | J40: LIVE Comfort Tank Top | N40: 2 | O40: 1 | P40: =SUM(K40:O40) -> 3 | Q40: =VLOOKUP(A40,'SOLVER NOVO'!A:E,5,FALSE) -> 7.817765 | R40: =Q40*P40 -> 23.453295
A41: P1213 | B41: 6106.20.10.10 | C41: 00BC14 | D41: Of man-made fibres | E41: Activewear Clothes, Knit. | F41: =VLOOKUP(A41,'[2]Todas Coleções'!$A:$E,5,FALSE) -> 100% PA | G41: =_xlfn.IMAGE(H41) -> #VALUE! | H41: =VLOOKUP(I41,[3]exportarImagens_10_07_2026_09_4!$C:$D,2,FALSE) -> https://imagens.liveoficial.com.br/product/80x120/515483_P1213_00BC14_2.jpg | I41: =A41&C41 -> P121300BC14 | J41: LIVE Comfort Crop Tank | L41: 2 | M41: 2 | O41: 1 | P41: =SUM(K41:O41) -> 5 | Q41: =VLOOKUP(A41,'SOLVER NOVO'!A:E,5,FALSE) -> 8.7312149 | R41: =Q41*P41 -> 43.656075
A42: P1213 | B42: 6106.20.10.10 | C42: 00RX80 | D42: Of man-made fibres | E42: Activewear Clothes, Knit. | F42: =VLOOKUP(A42,'[2]Todas Coleções'!$A:$E,5,FALSE) -> 100% PA | G42: =_xlfn.IMAGE(H42) -> #VALUE! | H42: =VLOOKUP(I42,[3]exportarImagens_10_07_2026_09_4!$C:$D,2,FALSE) -> https://imagens.liveoficial.com.br/product/80x120/508194_P1213_00RX80_2.jpg | I42: =A42&C42 -> P121300RX80 | J42: LIVE Comfort Crop Tank | M42: 2 | O42: 1 | P42: =SUM(K42:O42) -> 3 | Q42: =VLOOKUP(A42,'SOLVER NOVO'!A:E,5,FALSE) -> 8.7312149 | R42: =Q42*P42 -> 26.193645
A43: P1222 | B43: 6114.30.30.30 | C43: 00BC14 | D43: Of man-made fibres | E43: Activewear Clothes, Knit. | F43: =VLOOKUP(A43,'[2]Todas Coleções'!$A:$E,5,FALSE) -> 87% PA / 13% EL | G43: =_xlfn.IMAGE(H43) -> #VALUE! | H43: =VLOOKUP(I43,[3]exportarImagens_10_07_2026_09_4!$C:$D,2,FALSE) -> https://imagens.liveoficial.com.br/product/80x120/512561_P1222_00BC14_1.jpg | I43: =A43&C43 -> P122200BC14 | J43: LIVE Move Bra | M43: 3 | N43: 2 | P43: =SUM(K43:O43) -> 5 | Q43: =VLOOKUP(A43,'SOLVER NOVO'!A:E,5,FALSE) -> 9.0584904 | R43: =Q43*P43 -> 45.292452
A44: P1225 | B44: 6104.63.10.20 | C44: 00RX80 | D44: Of synthetic fibres | E44: Activewear Clothes, Knit. | F44: =VLOOKUP(A44,'[2]Todas Coleções'!$A:$E,5,FALSE) -> 88% PA / 12% EL | G44: =_xlfn.IMAGE(H44) -> #VALUE! | H44: =VLOOKUP(I44,[3]exportarImagens_10_07_2026_09_4!$C:$D,2,FALSE) -> https://imagens.liveoficial.com.br/product/80x120/507052_P1225_00RX80_1.jpg | I44: =A44&C44 -> P122500RX80 | J44: LIVE Icon Neo Short | M44: 3 | P44: =SUM(K44:O44) -> 3 | Q44: =VLOOKUP(A44,'SOLVER NOVO'!A:E,5,FALSE) -> 8.7623457 | R44: =Q44*P44 -> 26.287037
A45: P1226 | B45: 6104.63.10.20 | C45: 00RX80 | D45: Of synthetic fibres | E45: Activewear Clothes, Knit. | F45: =VLOOKUP(A45,'[2]Todas Coleções'!$A:$E,5,FALSE) -> 88% PA / 12% EL | G45: =_xlfn.IMAGE(H45) -> #VALUE! | H45: =VLOOKUP(I45,[3]exportarImagens_10_07_2026_09_4!$C:$D,2,FALSE) -> https://imagens.liveoficial.com.br/product/80x120/502465_P1226_00RX80_1.jpg | I45: =A45&C45 -> P122600RX80 | J45: LIVE Icon Neo Full Legging | L45: 3 | M45: 2 | P45: =SUM(K45:O45) -> 5 | Q45: =VLOOKUP(A45,'SOLVER NOVO'!A:E,5,FALSE) -> 10.234378 | R45: =Q45*P45 -> 51.171889
A46: P1298 | B46: 6114.30.30.30 | C46: 00RX80 | D46: Of man-made fibres | E46: Activewear Clothes, Knit. | F46: =VLOOKUP(A46,'[2]Todas Coleções'!$A:$E,5,FALSE) -> 88% PA / 12% EL | G46: =_xlfn.IMAGE(H46) -> #VALUE! | H46: =VLOOKUP(I46,[3]exportarImagens_10_07_2026_09_4!$C:$D,2,FALSE) -> https://imagens.liveoficial.com.br/product/80x120/501429_P1298_00RX80_2.jpg | I46: =A46&C46 -> P129800RX80 | J46: LIVE Icon Neo Bra | L46: 3 | M46: 2 | N46: 1 | P46: =SUM(K46:O46) -> 6 | Q46: =VLOOKUP(A46,'SOLVER NOVO'!A:E,5,FALSE) -> 10.644185 | R46: =Q46*P46 -> 63.865108
A47: P1434 | B47: 6114.30.30.30 | C47: 00RX80 | D47: Of man-made fibres | E47: Activewear Clothes, Knit. | F47: =VLOOKUP(A47,'[2]Todas Coleções'!$A:$E,5,FALSE) -> 90% PA / 10% EL | G47: =_xlfn.IMAGE(H47) -> #VALUE! | H47: =VLOOKUP(I47,[3]exportarImagens_10_07_2026_09_4!$C:$D,2,FALSE) -> https://imagens.liveoficial.com.br/product/80x120/508016_P1434_00RX80_2.jpg | I47: =A47&C47 -> P143400RX80 | J47: Sense Curve Bra | K47: 1 | L47: 3 | M47: 3 | N47: 2 | O47: 1 | P47: =SUM(K47:O47) -> 10 | Q47: =VLOOKUP(A47,'SOLVER NOVO'!A:E,5,FALSE) -> 7.0815216 | R47: =Q47*P47 -> 70.815216
A48: P1437 | B48: 6114.30.30.30 | C48: 00BC14 | D48: Of man-made fibres | E48: Activewear Clothes, Knit. | F48: =VLOOKUP(A48,'[2]Todas Coleções'!$A:$E,5,FALSE) -> 87% PA / 13% EL | G48: =_xlfn.IMAGE(H48) -> #VALUE! | H48: =VLOOKUP(I48,[3]exportarImagens_10_07_2026_09_4!$C:$D,2,FALSE) -> https://imagens.liveoficial.com.br/product/80x120/514774_P1437_00BC14_3.jpg | I48: =A48&C48 -> P143700BC14 | J48: LIVE Short Bodysuit | L48: 3 | M48: 2 | N48: 1 | P48: =SUM(K48:O48) -> 6 | Q48: =VLOOKUP(A48,'SOLVER NOVO'!A:E,5,FALSE) -> 8.7935381 | R48: =Q48*P48 -> 52.761229
A49: P1472 | B49: 6104.63.10.20 | C49: 00BC14 | D49: Of synthetic fibres | E49: Activewear Clothes, Knit. | F49: =VLOOKUP(A49,'[2]Todas Coleções'!$A:$E,5,FALSE) -> 87% PA / 13% EL | G49: =_xlfn.IMAGE(H49) -> #VALUE! | H49: =VLOOKUP(I49,[3]exportarImagens_10_07_2026_09_4!$C:$D,2,FALSE) -> https://imagens.liveoficial.com.br/product/80x120/512564_P1472_00BC14_1.jpg | I49: =A49&C49 -> P147200BC14 | J49: LIVE Full Length Legging | L49: 3 | M49: 3 | N49: 2 | P49: =SUM(K49:O49) -> 8 | Q49: =VLOOKUP(A49,'SOLVER NOVO'!A:E,5,FALSE) -> 6.7037163 | R49: =Q49*P49 -> 53.629731
A50: P1479 | B50: 6104.63.10.20 | C50: 00BC14 | D50: Of synthetic fibres | E50: Activewear Clothes, Knit. | F50: =VLOOKUP(A50,'[2]Todas Coleções'!$A:$E,5,FALSE) -> 87% PA / 13% EL | G50: =_xlfn.IMAGE(H50) -> #VALUE! | H50: =VLOOKUP(I50,[3]exportarImagens_10_07_2026_09_4!$C:$D,2,FALSE) -> https://imagens.liveoficial.com.br/product/80x120/515433_P1479_00BC14_1.jpg | I50: =A50&C50 -> P147900BC14 | J50: LIVE Fit Short | K50: 1 | M50: 2 | P50: =SUM(K50:O50) -> 3 | Q50: =VLOOKUP(A50,'SOLVER NOVO'!A:E,5,FALSE) -> 10.655789 | R50: =Q50*P50 -> 31.967367
A51: P1497 | B51: 6104.63.10.20 | C51: 00BC01 | D51: Of synthetic fibres | E51: Activewear Clothes, Knit. | F51: =VLOOKUP(A51,'[2]Todas Coleções'!$A:$E,5,FALSE) -> 88% PA / 12% EL | G51: =_xlfn.IMAGE(H51) -> #VALUE! | H51: =VLOOKUP(I51,[3]exportarImagens_10_07_2026_09_4!$C:$D,2,FALSE) -> https://imagens.liveoficial.com.br/product/80x120/499638_P1497_00BC01_1.jpg | I51: =A51&C51 -> P149700BC01 | J51: Maxi LIVE Short | L51: 10 | M51: 6 | N51: 4 | O51: 1 | P51: =SUM(K51:O51) -> 21 | Q51: =VLOOKUP(A51,'SOLVER NOVO'!A:E,5,FALSE) -> 9.5763917 | R51: =Q51*P51 -> 201.10423
A52: P1498 | B52: 6104.63.10.20 | C52: 0AZ190 | D52: Of synthetic fibres | E52: Activewear Clothes, Knit. | F52: =VLOOKUP(A52,'[2]Todas Coleções'!$A:$E,5,FALSE) -> 88% PA / 12% EL | G52: =_xlfn.IMAGE(H52) -> #VALUE! | H52: =VLOOKUP(I52,[3]exportarImagens_10_07_2026_09_4!$C:$D,2,FALSE) -> https://imagens.liveoficial.com.br/product/80x120/522116_P1498_0AZ190_1.jpg | I52: =A52&C52 -> P14980AZ190 | J52: Maxi LIVE Leggings | N52: 1 | P52: =SUM(K52:O52) -> 1 | Q52: =VLOOKUP(A52,'SOLVER NOVO'!A:E,5,FALSE) -> 8.4328336 | R52: =Q52*P52 -> 8.4328336
A53: P1499 | B53: 6202.40.15.10 | C53: 00BC01 | D53: Of synthetic fibres | E53: Activewear Clothes, Knit. | F53: =VLOOKUP(A53,'[2]Todas Coleções'!$A:$E,5,FALSE) -> 90% PES / 10% EL | G53: =_xlfn.IMAGE(H53) -> #VALUE! | H53: =VLOOKUP(I53,[3]exportarImagens_10_07_2026_09_4!$C:$D,2,FALSE) -> https://imagens.liveoficial.com.br/product/80x120/515095_P1499_00BC01_2.jpg | I53: =A53&C53 -> P149900BC01 | J53: Maxi LIVE Jacket | N53: 4 | P53: =SUM(K53:O53) -> 4 | Q53: =VLOOKUP(A53,'SOLVER NOVO'!A:E,5,FALSE) -> 12.359676 | R53: =Q53*P53 -> 49.438705
A54: P1559 | B54: 6104.63.10.20 | C54: 0AZ190 | D54: Of synthetic fibres | E54: Activewear Clothes, Knit. | F54: =VLOOKUP(A54,'[2]Todas Coleções'!$A:$E,5,FALSE) -> 88% PA / 12% EL | G54: =_xlfn.IMAGE(H54) -> #VALUE! | H54: =VLOOKUP(I54,[3]exportarImagens_10_07_2026_09_4!$C:$D,2,FALSE) -> https://imagens.liveoficial.com.br/product/80x120/512610_P1559_0AZ190_2.jpg | I54: =A54&C54 -> P15590AZ190 | J54: Hydefit Adaptiv Legging | N54: 2 | O54: 1 | P54: =SUM(K54:O54) -> 3 | Q54: =VLOOKUP(A54,'SOLVER NOVO'!A:E,5,FALSE) -> 9.9844301 | R54: =Q54*P54 -> 29.95329
A55: P1560 | B55: 6114.30.30.30 | C55: 00BC01 | D55: Of man-made fibres | E55: Activewear Clothes, Knit. | F55: =VLOOKUP(A55,'[2]Todas Coleções'!$A:$E,5,FALSE) -> 88% PA / 12% EL | G55: =_xlfn.IMAGE(H55) -> #VALUE! | H55: =VLOOKUP(I55,[3]exportarImagens_10_07_2026_09_4!$C:$D,2,FALSE) -> https://imagens.liveoficial.com.br/product/80x120/515136_P1560_00BC01_2.jpg | I55: =A55&C55 -> P156000BC01 | J55: Reversible LIVE Multi Bra | N55: 1 | O55: 3 | P55: =SUM(K55:O55) -> 4 | Q55: =VLOOKUP(A55,'SOLVER NOVO'!A:E,5,FALSE) -> 12.427872 | R55: =Q55*P55 -> 49.711489
A56: P1560 | B56: 6114.30.30.30 | C56: 0AZ190 | D56: Of man-made fibres | E56: Activewear Clothes, Knit. | F56: =VLOOKUP(A56,'[2]Todas Coleções'!$A:$E,5,FALSE) -> 88% PA / 12% EL | G56: =_xlfn.IMAGE(H56) -> #VALUE! | H56: =VLOOKUP(I56,[3]exportarImagens_10_07_2026_09_4!$C:$D,2,FALSE) -> https://imagens.liveoficial.com.br/product/80x120/522063_P1560_0AZ190_1.jpg | I56: =A56&C56 -> P15600AZ190 | J56: Reversible LIVE Multi Bra | M56: 2 | P56: =SUM(K56:O56) -> 2 | Q56: =VLOOKUP(A56,'SOLVER NOVO'!A:E,5,FALSE) -> 12.427872 | R56: =Q56*P56 -> 24.855745
A57: P1581 | B57: 6104.63.10.20 | C57: 00BC01 | D57: Of synthetic fibres | E57: Activewear Clothes, Knit. | F57: =VLOOKUP(A57,'[2]Todas Coleções'!$A:$E,5,FALSE) -> 82% PA / 18% EL | G57: =_xlfn.IMAGE(H57) -> #VALUE! | H57: =VLOOKUP(I57,[3]exportarImagens_10_07_2026_09_4!$C:$D,2,FALSE) -> https://imagens.liveoficial.com.br/product/80x120/514680_P1581_00BC01_2.jpg | I57: =A57&C57 -> P158100BC01 | J57: Allure Adaptiv Fit Shorts | L57: 4 | M57: 3 | N57: 2 | P57: =SUM(K57:O57) -> 9 | Q57: =VLOOKUP(A57,'SOLVER NOVO'!A:E,5,FALSE) -> 11.493431 | R57: =Q57*P57 -> 103.44088
A58: P1589 | B58: 6114.30.30.30 | C58: 00BC14 | D58: Of man-made fibres | E58: Activewear Clothes, Knit. | F58: =VLOOKUP(A58,'[2]Todas Coleções'!$A:$E,5,FALSE) -> 88% PA / 12% EL | G58: =_xlfn.IMAGE(H58) -> #VALUE! | H58: =VLOOKUP(I58,[3]exportarImagens_10_07_2026_09_4!$C:$D,2,FALSE) -> https://imagens.liveoficial.com.br/product/80x120/514355_P1589_00BC14_1.jpg | I58: =A58&C58 -> P158900BC14 | J58: Top LIVE Icon | L58: 3 | M58: 3 | N58: 2 | O58: 1 | P58: =SUM(K58:O58) -> 9 | Q58: =VLOOKUP(A58,'SOLVER NOVO'!A:E,5,FALSE) -> 8.6023105 | R58: =Q58*P58 -> 77.420795
A59: P1590 | B59: 6104.63.10.20 | C59: 00BC14 | D59: Of synthetic fibres | E59: Activewear Clothes, Knit. | F59: =VLOOKUP(A59,'[2]Todas Coleções'!$A:$E,5,FALSE) -> 88% PA / 12% EL | G59: =_xlfn.IMAGE(H59) -> #VALUE! | H59: =VLOOKUP(I59,[3]exportarImagens_10_07_2026_09_4!$C:$D,2,FALSE) -> https://imagens.liveoficial.com.br/product/80x120/514348_P1590_00BC14_1.jpg | I59: =A59&C59 -> P159000BC14 | J59: LIVE Icon Fit Short | L59: 3 | N59: 2 | O59: 1 | P59: =SUM(K59:O59) -> 6 | Q59: =VLOOKUP(A59,'SOLVER NOVO'!A:E,5,FALSE) -> 10.743889 | R59: =Q59*P59 -> 64.463337
A60: P1591 | B60: 6104.63.10.20 | C60: 00BC14 | D60: Of synthetic fibres | E60: Activewear Clothes, Knit. | F60: =VLOOKUP(A60,'[2]Todas Coleções'!$A:$E,5,FALSE) -> 88% PA / 12% EL | G60: =_xlfn.IMAGE(H60) -> #VALUE! | H60: =VLOOKUP(I60,[3]exportarImagens_10_07_2026_09_4!$C:$D,2,FALSE) -> https://imagens.liveoficial.com.br/product/80x120/515310_P1591_00BC14_1.jpg | I60: =A60&C60 -> P159100BC14 | J60: LIVE Icon Legging | L60: 2 | M60: 2 | O60: 1 | P60: =SUM(K60:O60) -> 5 | Q60: =VLOOKUP(A60,'SOLVER NOVO'!A:E,5,FALSE) -> 10.493545 | R60: =Q60*P60 -> 52.467727
A61: P1593 | B61: 6109.90.80.10 | C61: 00BC01 | D61: Of other textile materials | E61: Activewear Clothes, Knit. | F61: =VLOOKUP(A61,'[2]Todas Coleções'!$A:$E,5,FALSE) -> 92% PA / 8% EL | G61: =_xlfn.IMAGE(H61) -> #VALUE! | H61: =VLOOKUP(I61,[3]exportarImagens_10_07_2026_09_4!$C:$D,2,FALSE) -> https://imagens.liveoficial.com.br/product/80x120/515669_P1593_00BC01_2.jpg | I61: =A61&C61 -> P159300BC01 | J61: Thermo Skin LS T Shirt | L61: 3 | N61: 2 | P61: =SUM(K61:O61) -> 5 | Q61: =VLOOKUP(A61,'SOLVER NOVO'!A:E,5,FALSE) -> 10.597997 | R61: =Q61*P61 -> 52.989984
A62: P1596 | B62: 6104.63.10.20 | C62: 00BC01 | D62: Of synthetic fibres | E62: Activewear Clothes, Knit. | F62: =VLOOKUP(A62,'[2]Todas Coleções'!$A:$E,5,FALSE) -> 88% PA / 12% EL | G62: =_xlfn.IMAGE(H62) -> #VALUE! | H62: =VLOOKUP(I62,[3]exportarImagens_10_07_2026_09_4!$C:$D,2,FALSE) -> https://imagens.liveoficial.com.br/product/80x120/515131_P1596_00BC01_1837.jpg | I62: =A62&C62 -> P159600BC01 | J62: Maxi LIVE Leggings | L62: 8 | O62: 2 | P62: =SUM(K62:O62) -> 10 | Q62: =VLOOKUP(A62,'SOLVER NOVO'!A:E,5,FALSE) -> 8.993111 | R62: =Q62*P62 -> 89.93111
A63: P1601 | B63: 6102.20.00.10 | C63: 00BC01 | D63: Of cotton | E63: Activewear Clothes, Knit. | F63: =VLOOKUP(A63,'[2]Todas Coleções'!$A:$E,5,FALSE) -> 68% CO / 32% PES | G63: =_xlfn.IMAGE(H63) -> #VALUE! | H63: =VLOOKUP(I63,[3]exportarImagens_10_07_2026_09_4!$C:$D,2,FALSE) -> https://imagens.liveoficial.com.br/product/80x120/508669_P1601_00BC01_1.jpg | I63: =A63&C63 -> P160100BC01 | J63: Welfare Hoodie | K63: 3 | L63: 3 | M63: 2 | N63: 1 | P63: =SUM(K63:O63) -> 9 | Q63: =VLOOKUP(A63,'SOLVER NOVO'!A:E,5,FALSE) -> 10.754326 | R63: =Q63*P63 -> 96.788935
A64: P1602 | B64: 6104.62.10.20 | C64: 00BC01 | D64: Of cotton | E64: Activewear Clothes, Knit. | F64: =VLOOKUP(A64,'[2]Todas Coleções'!$A:$E,5,FALSE) -> 68% CO / 32% PES | G64: =_xlfn.IMAGE(H64) -> #VALUE! | H64: =VLOOKUP(I64,[3]exportarImagens_10_07_2026_09_4!$C:$D,2,FALSE) -> https://imagens.liveoficial.com.br/product/80x120/508700_P1602_00BC01_2.jpg | I64: =A64&C64 -> P160200BC01 | J64: Welfare Short | K64: 2 | N64: 1 | P64: =SUM(K64:O64) -> 3 | Q64: =VLOOKUP(A64,'SOLVER NOVO'!A:E,5,FALSE) -> 10.570831 | R64: =Q64*P64 -> 31.712492
A65: P1603 | B65: 6104.62.10.20 | C65: 00BC01 | D65: Of cotton | E65: Activewear Clothes, Knit. | F65: =VLOOKUP(A65,'[2]Todas Coleções'!$A:$E,5,FALSE) -> 68% CO / 32% PES | G65: =_xlfn.IMAGE(H65) -> #VALUE! | H65: =VLOOKUP(I65,[3]exportarImagens_10_07_2026_09_4!$C:$D,2,FALSE) -> https://imagens.liveoficial.com.br/product/80x120/506606_P1603_00BC01_1.jpg | I65: =A65&C65 -> P160300BC01 | J65: Welfare Jogger Pant | K65: 3 | L65: 1 | M65: 2 | N65: 1 | P65: =SUM(K65:O65) -> 7 | Q65: =VLOOKUP(A65,'SOLVER NOVO'!A:E,5,FALSE) -> 9.961564 | R65: =Q65*P65 -> 69.730948
A66: P1628 | B66: 6102.30.20.10 | C66: 0AZ190 | D66: Of man-made fibres | E66: Activewear Clothes, Knit. | F66: =VLOOKUP(A66,'[2]Todas Coleções'!$A:$E,5,FALSE) -> 91% PA / 9% EL | G66: =_xlfn.IMAGE(H66) -> #VALUE! | H66: =VLOOKUP(I66,[3]exportarImagens_10_07_2026_09_4!$C:$D,2,FALSE) -> https://imagens.liveoficial.com.br/product/80x120/522330_P1628_0AZ190_3.jpg | I66: =A66&C66 -> P16280AZ190 | J66: Harmony Jacket Pro | K66: 1 | N66: 1 | P66: =SUM(K66:O66) -> 2 | Q66: =VLOOKUP(A66,'SOLVER NOVO'!A:E,5,FALSE) -> 10.504166 | R66: =Q66*P66 -> 21.008332
A67: P1629 | B67: 6114.30.30.30 | C67: 0AZ190 | D67: Of man-made fibres | E67: Activewear Clothes, Knit. | F67: =VLOOKUP(A67,'[2]Todas Coleções'!$A:$E,5,FALSE) -> 76% PA / 24% EL | G67: =_xlfn.IMAGE(H67) -> #VALUE! | H67: =VLOOKUP(I67,[3]exportarImagens_10_07_2026_09_4!$C:$D,2,FALSE) -> https://imagens.liveoficial.com.br/product/80x120/508215_P1629_0AZ190_3.jpg | I67: =A67&C67 -> P16290AZ190 | J67: Speed Bra | K67: 2 | L67: 3 | M67: 2 | N67: 2 | P67: =SUM(K67:O67) -> 9 | Q67: =VLOOKUP(A67,'SOLVER NOVO'!A:E,5,FALSE) -> 10.702448 | R67: =Q67*P67 -> 96.322034
A68: P1666 | B68: 6114.30.30.30 | C68: 00BC01 | D68: Of man-made fibres | E68: Activewear Clothes, Knit. | F68: =VLOOKUP(A68,'[2]Todas Coleções'!$A:$E,5,FALSE) -> 90% PA / 10% EL | G68: =_xlfn.IMAGE(H68) -> #VALUE! | H68: =VLOOKUP(I68,[3]exportarImagens_10_07_2026_09_4!$C:$D,2,FALSE) -> https://imagens.liveoficial.com.br/product/80x120/512624_P1666_00BC01_2.jpg | I68: =A68&C68 -> P166600BC01 | J68: Sense Motion Slim Bra | K68: 1 | L68: 4 | P68: =SUM(K68:O68) -> 5 | Q68: =VLOOKUP(A68,'SOLVER NOVO'!A:E,5,FALSE) -> 10.920884 | R68: =Q68*P68 -> 54.60442
A69: P1927 | B69: 6106.20.10.10 | C69: 00BC01 | D69: Of man-made fibres | E69: Activewear Clothes, Knit. | F69: =VLOOKUP(A69,'[2]Todas Coleções'!$A:$E,5,FALSE) -> 90% PA / 10% EL | G69: =_xlfn.IMAGE(H69) -> #VALUE! | H69: =VLOOKUP(I69,[3]exportarImagens_10_07_2026_09_4!$C:$D,2,FALSE) -> https://imagens.liveoficial.com.br/product/80x120/511807_P1927_00BC01_1807.jpg | I69: =A69&C69 -> P192700BC01 | J69: Sense Move Crop Tank | K69: 3 | L69: 5 | N69: 3 | P69: =SUM(K69:O69) -> 11 | Q69: =VLOOKUP(A69,'SOLVER NOVO'!A:E,5,FALSE) -> 11.437603 | R69: =Q69*P69 -> 125.81363
A70: P6200 | B70: 6114.30.30.30 | C70: 00BC01 | D70: Of man-made fibres | E70: Activewear Clothes, Knit. | F70: =VLOOKUP(A70,'[2]Todas Coleções'!$A:$E,5,FALSE) -> 90% PA / 10% EL | G70: =_xlfn.IMAGE(H70) -> #VALUE! | H70: =VLOOKUP(I70,[3]exportarImagens_10_07_2026_09_4!$C:$D,2,FALSE) -> https://imagens.liveoficial.com.br/product/80x120/512641_P6200_00BC01_2.jpg | I70: =A70&C70 -> P620000BC01 | J70: Sense Slim BT Bra | L70: 3 | N70: 2 | P70: =SUM(K70:O70) -> 5 | Q70: =VLOOKUP(A70,'SOLVER NOVO'!A:E,5,FALSE) -> 12.150155 | R70: =Q70*P70 -> 60.750776
A71: P6200 | B71: 6114.30.30.30 | C71: 00RX80 | D71: Of man-made fibres | E71: Activewear Clothes, Knit. | F71: =VLOOKUP(A71,'[2]Todas Coleções'!$A:$E,5,FALSE) -> 90% PA / 10% EL | G71: =_xlfn.IMAGE(H71) -> #VALUE! | H71: =VLOOKUP(I71,[3]exportarImagens_10_07_2026_09_4!$C:$D,2,FALSE) -> https://imagens.liveoficial.com.br/product/80x120/508199_P6200_00RX80_2.jpg | I71: =A71&C71 -> P620000RX80 | J71: Sense Slim BT Bra | K71: 1 | M71: 3 | N71: 2 | P71: =SUM(K71:O71) -> 6 | Q71: =VLOOKUP(A71,'SOLVER NOVO'!A:E,5,FALSE) -> 12.150155 | R71: =Q71*P71 -> 72.900932
P72: =SUM(P30:P71) -> 236 | R72: =SUM(R30:R71) -> 2327.8638
R77: 5.1737
R78: =R72*R77 -> 12043.669

Sheet invoice
A1: Order | B1: Reference | C1: N.C.M. | D1: Color | E1: Product Materials | F1: Composition | G1: Description | H1: XS | I1: S | J1: M | K1: L | L1: XL
A2: 2799646 | B2: 46586 | C2: 6114.30.30.30 | D2: 00RX80 | E2: Of man-made fibres | F2: BODY: 8% ELASTANE / 92% POLYAMIDE - LINING: 10% ELASTANE / 90% POLYAMIDE | G2: Melt Square Bra | J2: 3 | K2: 2
A3: 2799646 | B3: 46588 | C3: 6104.63.10.20 | D3: 00RX80 | E3: Of synthetic fibres | F3: BODY: 8% ELASTANE / 92% POLYAMIDE - LINING: 10% ELASTANE / 90% POLYAMIDE | G3: Melt Square Full Legging | J3: 2
A4: 2799646 | B4: 46589 | C4: 6104.63.10.20 | D4: 00RX80 | E4: Of synthetic fibres | F4: 8% ELASTANE / 92% POLYAMIDE | G4: Square Melt Ballerina Pants | I4: 2
A5: 2799646 | B5: 46591 | C5: 6104.63.10.20 | D5: 00RX80 | E5: Of synthetic fibres | F5: 3% ELASTANE / 97% POLYAMIDE | G5: Seamless Mesh Full Legging | I5: 2 | J5: 2
A6: 2799646 | B6: 46592 | C6: 6114.30.30.30 | D6: 00RX80 | E6: Of man-made fibres | F6: 3% ELASTANE / 97% POLYAMIDE | G6: Seamless Knit Short Bodysuit | H6: 1 | I6: 3
A7: 2799646 | B7: P0063 | C7: 6114.30.30.30 | D7: 00BC14 | E7: Of man-made fibres | F7: BODY/LINING: 14% ELASTANE / 86% POLYAMIDE / - OUTSIDE / LINING: 14% ELASTANE / 41% POLYESTER / 45% POLYAMIDE / - OUTSIDE/LINING: 13% ELASTANE / 14% ELASTANE / 86% POLYAMIDE / 87% POLYAMIDE / - 13% ELASTANE / 14% ELASTANE / 41% POLYESTER / 45% POLYAMIDE / 87% POLYAMIDE | G7: LIVE Curve Bra | H7: 1 | I7: 3 | L7: 1
A8: 2799646 | B8: P1153 | C8: 6109.90.80.10 | D8: 00BC14 | E8: Of other textile materials | F8: 100% POLYAMIDE | G8: LIVE Comfort TShirt | H8: 1 | I8: 3 | J8: 3 | K8: 1 | L8: 1
A9: 2799646 | B9: P1153 | C9: 6109.90.80.10 | D9: 00RX80 | E9: Of other textile materials | F9: 100% POLYAMIDE | G9: LIVE Comfort TShirt | I9: 3 | K9: 2
A10: 2799646 | B10: P1153 | C10: 6109.90.80.10 | D10: 0AZ190 | E10: Of other textile materials | F10: 100% POLYAMIDE | G10: LIVE Comfort TShirt | H10: 1 | I10: 2 | K10: 1
A11: 2799646 | B11: P1154 | C11: 6106.20.10.10 | D11: 00BC14 | E11: Of man-made fibres | F11: 100% POLYAMIDE | G11: LIVE Comfort Tank Top | I11: 3
A12: 2799646 | B12: P1154 | C12: 6106.20.10.10 | D12: 00RX80 | E12: Of man-made fibres | F12: 100% POLYAMIDE | G12: LIVE Comfort Tank Top | K12: 2 | L12: 1
A13: 2799646 | B13: P1213 | C13: 6106.20.10.10 | D13: 00BC14 | E13: Of man-made fibres | F13: 100% POLYAMIDE | G13: LIVE Comfort Crop Tank | I13: 2 | J13: 2 | L13: 1
A14: 2799646 | B14: P1213 | C14: 6106.20.10.10 | D14: 00RX80 | E14: Of man-made fibres | F14: 100% POLYAMIDE | G14: LIVE Comfort Crop Tank | J14: 2 | L14: 1
A15: 2799646 | B15: P1222 | C15: 6114.30.30.30 | D15: 00BC14 | E15: Of man-made fibres | F15: BODY: 13% ELASTANE / 87% POLYAMIDE / - BODY AND LINING: 13% ELASTANE / 87% POLYAMIDE - LINING: 10% ELASTANE / 90% POLYAMIDE / 92% POLYESTER / - LININIG: 10% ELASTANE / 8% ELASTANE / - OUTSIDE: 13% ELASTANE / 87% POLYAMIDE / - 13% ELASTANE / 14% ELASTANE / 41% POLYESTER / 45% POLYAMIDE / 86% POLYAMIDE / 87% POLYAMIDE | G15: LIVE Move Bra | J15: 3 | K15: 2
A16: 2799646 | B16: P1225 | C16: 6104.63.10.20 | D16: 00RX80 | E16: Of synthetic fibres | F16: BODY: 12% ELASTANE / 88% POLYAMIDE / - 12% ELASTANE / 88% POLYAMIDE | G16: LIVE Icon Neo Short | J16: 3
A17: 2799646 | B17: P1226 | C17: 6104.63.10.20 | D17: 00RX80 | E17: Of synthetic fibres | F17: BODY: 12% ELASTANE / 88% POLYAMIDE / - 12% ELASTANE / 88% POLYAMIDE | G17: LIVE Icon Neo Full Legging | I17: 3 | J17: 2
A18: 2799646 | B18: P1298 | C18: 6114.30.30.30 | D18: 00RX80 | E18: Of man-made fibres | F18: BODY: 12% ELASTANE / 88% POLYAMIDE - LINING: 10% ELASTANE / 90% POLYAMIDE / - OUTSIDE: 12% ELASTANE / 88% POLYAMIDE | G18: LIVE Icon Neo Bra | I18: 3 | J18: 2 | K18: 1
A19: 2799646 | B19: P1434 | C19: 6114.30.30.30 | D19: 00RX80 | E19: Of man-made fibres | F19: BODY AND LINING: 10% ELASTANE / 90% POLYAMIDE / - BODY/LINING: 10% ELASTANE / 7% ELASTANE / 90% POLYAMIDE / 93% POLYAMIDE / - OUTSIDE / LINING: 10% ELASTANE / 44% POLYESTER / 49% POLYAMIDE / 7% ELASTANE / 90% POLYAMIDE / 93% POLYAMIDE / - OUTSIDE/LINING: 10% ELASTANE / 44% POLYESTER / 49% POLYAMIDE / 7% ELASTANE / 90% POLYAMIDE / - 10% ELASTANE / 90% POLYAMIDE | G19: Sense Curve Bra | H19: 1 | I19: 3 | J19: 3 | K19: 2 | L19: 1
A20: 2799646 | B20: P1437 | C20: 6114.30.30.30 | D20: 00BC14 | E20: Of man-made fibres | F20: BODY: 13% ELASTANE / 14% ELASTANE / 86% POLYAMIDE / 87% POLYAMIDE - LINING: 10% ELASTANE / 7% ELASTANE / 8% ELASTANE / 90% POLYAMIDE / 92% POLYAMIDE / 93% POLYAMIDE / - 10% ELASTANE / 13% ELASTANE / 87% POLYAMIDE / 90% POLYAMIDE | G20: LIVE Short Bodysuit | I20: 3 | J20: 2 | K20: 1
A21: 2799646 | B21: P1472 | C21: 6104.63.10.20 | D21: 00BC14 | E21: Of synthetic fibres | F21: BODY: 13% ELASTANE / 13% ELASTANE / 87% POLYAMIDE / 87% POLYAMIDE - LINING: 10% ELASTANE / 7% ELASTANE / 8% ELASTANE / 90% POLYAMIDE / 92% POLYAMIDE / 93% POLYAMIDE | G21: LIVE Full Length Legging | I21: 3 | J21: 3 | K21: 2
A22: 2799646 | B22: P1479 | C22: 6104.63.10.20 | D22: 00BC14 | E22: Of synthetic fibres | F22: BODY: 13% ELASTANE / 87% POLYAMIDE - LINING: 10% ELASTANE / 7% ELASTANE / 90% POLYAMIDE / 93% POLYAMIDE / - 13% ELASTANE / 87% POLYAMIDE | G22: LIVE Fit Short | H22: 1 | J22: 2
A23: 2799646 | B23: P1497 | C23: 6104.63.10.20 | D23: 00BC01 | E23: Of synthetic fibres | F23: BODY: 12% ELASTANE / 88% POLYAMIDE - LINING: 10% ELASTANE / 90% POLYAMIDE / - 12% ELASTANE / 88% POLYAMIDE | G23: Maxi LIVE Short | I23: 10 | J23: 6 | K23: 4 | L23: 1
A24: 2799646 | B24: P1498 | C24: 6104.63.10.20 | D24: 0AZ190 | E24: Of synthetic fibres | F24: 12% ELASTANE / 88% POLYAMIDE | G24: Maxi LIVE Leggings | K24: 1
A25: 2799646 | B25: P1499 | C25: 6202.40.15.10 | D25: 00BC01 | E25: Of synthetic fibres | F25: BODY AND LINING: 10% ELASTANE / 90% POLYESTER | G25: Maxi LIVE Jacket | K25: 4
A26: 2799646 | B26: P1559 | C26: 6104.63.10.20 | D26: 0AZ190 | E26: Of synthetic fibres | F26: BODY: 12% ELASTANE / 12% ELASTANE / 88% POLYAMIDE / 88% POLYAMIDE - LINING: 10% ELASTANE / 7% ELASTANE / 7% ELASTANE / 8% ELASTANE / 90% POLYAMIDE / 92% POLYAMIDE / 93% POLYAMIDE / 93% POLYAMIDE | G26: Hydefit Adaptiv Legging | K26: 2 | L26: 1
A27: 2799646 | B27: P1560 | C27: 6114.30.30.30 | D27: 00BC01 | E27: Of man-made fibres | F27: PRINTEC FABRIC AND SOLID COLOR FABRIC: 12% ELASTANE / 88% POLYAMIDE / - PRINTED FABRIC AND SOLID COLOR FABRIC: 12% ELASTANE / 88% POLYAMIDE / - 12% ELASTANE / 88% POLYAMIDE | G27: Reversible LIVE Multi Bra | K27: 1 | L27: 3
A28: 2799646 | B28: P1560 | C28: 6114.30.30.30 | D28: 0AZ190 | E28: Of man-made fibres | F28: PRINTEC FABRIC AND SOLID COLOR FABRIC: 12% ELASTANE / 88% POLYAMIDE / - PRINTED FABRIC AND SOLID COLOR FABRIC: 12% ELASTANE / 88% POLYAMIDE / - 12% ELASTANE / 88% POLYAMIDE | G28: Reversible LIVE Multi Bra | J28: 2
A29: 2799646 | B29: P1581 | C29: 6104.63.10.20 | D29: 00BC01 | E29: Of synthetic fibres | F29: BODY: 18% ELASTANE / 82% POLYAMIDE - LINING: 10% ELASTANE / 90% POLYAMIDE | G29: Allure Adaptiv Fit Shorts | I29: 4 | J29: 3 | K29: 2
A30: 2799646 | B30: P1589 | C30: 6114.30.30.30 | D30: 00BC14 | E30: Of man-made fibres | F30: BODY: 12% ELASTANE / 88% POLYAMIDE - LINING: 10% ELASTANE / 90% POLYAMIDE | G30: Top LIVE Icon | I30: 3 | J30: 3 | K30: 2 | L30: 1
A31: 2799646 | B31: P1590 | C31: 6104.63.10.20 | D31: 00BC14 | E31: Of synthetic fibres | F31: BODY: 12% ELASTANE / 88% POLYAMIDE - LINING: 10% ELASTANE / 90% POLYAMIDE / - 12% ELASTANE / 88% POLYAMIDE | G31: LIVE Icon Fit Short | I31: 3 | K31: 2 | L31: 1
A32: 2799646 | B32: P1591 | C32: 6104.63.10.20 | D32: 00BC14 | E32: Of synthetic fibres | F32: BODY: 12% ELASTANE / 88% POLYAMIDE - LINING: 10% ELASTANE / 90% POLYAMIDE | G32: LIVE Icon Legging | I32: 2 | J32: 2 | L32: 1
A33: 2799646 | B33: P1593 | C33: 6109.90.80.10 | D33: 00BC01 | E33: Of other textile materials | F33: 8% ELASTANE / 92% POLYAMIDE | G33: Thermo Skin LS T Shirt | I33: 3 | K33: 2
A34: 2799646 | B34: P1596 | C34: 6104.63.10.20 | D34: 00BC01 | E34: Of synthetic fibres | F34: BODY: 12% ELASTANE / 88% POLYAMIDE - LINING: 10% ELASTANE / 90% POLYAMIDE | G34: Maxi LIVE Leggings | I34: 8 | L34: 2
A35: 2799646 | B35: P1601 | C35: 6102.20.00.10 | D35: 00BC01 | E35: Of cotton | F35: BODY AND HOOD LINING: 32% POLYESTER / 68% COTTON / - 32% POLYESTER / 68% COTTON | G35: Welfare Hoodie | H35: 3 | I35: 3 | J35: 2 | K35: 1
A36: 2799646 | B36: P1602 | C36: 6104.62.10.20 | D36: 00BC01 | E36: Of cotton | F36: BODY AND POCKET LINING: 32% POLYESTER / 68% COTTON / - 32% POLYESTER / 68% COTTON | G36: Welfare Short | H36: 2 | K36: 1
A37: 2799646 | B37: P1603 | C37: 6104.62.10.20 | D37: 00BC01 | E37: Of cotton | F37: BODY AND POCKET LINING: 32% POLYESTER / 32% POLYESTER / 68% COTTON / 68% COTTON / - 32% POLYESTER / 32% POLYESTER / 68% COTTON / 68% COTTON | G37: Welfare Jogger Pant | H37: 3 | I37: 1 | J37: 2 | K37: 1
A38: 2799646 | B38: P1628 | C38: 6102.30.20.10 | D38: 0AZ190 | E38: Of man-made fibres | F38: 8% ELASTANE / 9% ELASTANE / 91% POLYAMIDE / 92% POLYAMIDE | G38: Harmony Jacket Pro | H38: 1 | K38: 1
A39: 2799646 | B39: P1629 | C39: 6114.30.30.30 | D39: 0AZ190 | E39: Of man-made fibres | F39: BODY: 21% ELASTANE / 24% ELASTANE / 76% POLYAMIDE / 79% POLYAMIDE / - CUP COATING AND HANDLES LINING: 100% POLYESTER / 100% POLYESTER / - FRONT LINING: 10% ELASTANE / 10% ELASTANE / 90% POLYAMIDE / 90% POLYAMIDE | G39: Speed Bra | H39: 2 | I39: 3 | J39: 2 | K39: 2
A40: 2799646 | B40: P1666 | C40: 6114.30.30.30 | D40: 00BC01 | E40: Of man-made fibres | F40: 10% ELASTANE / 13% ELASTANE / 13% ELASTANE / 87% POLYAMIDE / 87% POLYAMIDE / 90% POLYAMIDE | G40: Sense Motion Slim Bra | H40: 1 | I40: 4
A41: 2799646 | B41: P1927 | C41: 6106.20.10.10 | D41: 00BC01 | E41: Of man-made fibres | F41: BODY: 10% ELASTANE / 10% ELASTANE / 90% POLYAMIDE / 90% POLYAMIDE / - BODY AND LINING: 10% ELASTANE / 90% POLYAMIDE - LINING: 7% ELASTANE / 8% ELASTANE / 92% POLYAMIDE / 93% POLYAMIDE | G41: Sense Move Crop Tank | H41: 3 | I41: 5 | K41: 3
A42: 2799646 | B42: P6200 | C42: 6114.30.30.30 | D42: 00BC01 | E42: Of man-made fibres | F42: BODY AND LINING: 10% ELASTANE / 90% POLYAMIDE | G42: Sense Slim BT Bra | I42: 3 | K42: 2
A43: 2799646 | B43: P6200 | C43: 6114.30.30.30 | D43: 00RX80 | E43: Of man-made fibres | F43: BODY AND LINING: 10% ELASTANE / 90% POLYAMIDE | G43: Sense Slim BT Bra | H43: 1 | J43: 3 | K43: 2

Sheet PACKING LIST
A1: PACKING LIST | M1: C-129/2026
A4: EXPORTER AND MANUFACTURER | M4: Date: 06/24/2026
A5: Live Roupas Esportivas LTDA | M5: Country of Origin: | N5: Port of Destiation
A6: Rua Manoel Francisco da Costa, 1600, Predio 01, Piso 02
A7: Vieira - Jaraguá do Sul - SC | M7: Jaraguá do Sul/BR | N7: Miami / USA
A8: Brasil | M8: Total Net Weight (kg): | N8: Total Gross Weight (kg):
A9: exports@liveoficial.com.br
A10: 89257-207 | M10: =N112 -> 34.32 | N10: =N116 -> 38.4
A11: Tel.: 55 47 2106-7400 | M11: Country of Origin: | N11: Carrier:
M12: Brazil | N12: 0
A13: CONSIGNEE | R13: =N10-M10 -> 4.08
A14: CLIENTE / CUSTOMER: | D14: LIVE! CLOTHING LLC - EIN 371775533
A15: CONTACT PERSON: | D15: Cintia Netto
A16: ENDEREÇO/ ADDRESS: | D16: 723 Lincoln Road
A17: CEP / ZIP CODE: | D17: 33139
A18: CIDADE / CITY: | D18: Miami
A19: PAÍS / COUNTRY: | D19: United States of America
A20: EMAIL: | D20: ecommerce@liveclothing.com
A21: TEL: | D21: (305) 537-4910 / (561) 543-5998
A22: CONSIGNATARIO / CONSIGNEE: | D22: LIVE! CLOTHING LLC - EIN 371775533
A23: CONTACT PERSON: | D23: Cintia Netto
A24: ENDEREÇO/ ADDRESS: | D24: 723 Lincoln Road
A25: CEP / ZIP CODE: | D25: 33139
A26: CIDADE / CITY: | D26: Miami
A27: PAÍS / COUNTRY: | D27: United States of America
A28: EMAIL: | D28: ecommerce@liveclothing.com
A29: TEL: | D29: (305) 537-4910 / (561) 543-5998
A30: INCOTERM: | B30: CIP
A31: TERMS OF PAYMENT: | C31: 365 Days After Invoice Date
A32: NOTE: PO 1586948
A33: BOX | B33: REFERENCE | C33: HS CODE | D33: COLOR | E33: PRODUCT MATERIAL | F33: DESCRIPTION | G33: XS | H33: S | I33: M | J33: L | K33: XL | L33: UNIT | M33: UNIT WEIGHT | N33: TOTAL WEIGHT
A34: 3744887 | B34: P1153 | C34: 6109.90.80.10 | D34: 00BC14 | E34: Of other textile materials | F34: LIVE Comfort TShirt | I34: 2 | K34: 1 | L34: =SUM(G34:K34) -> 3 | M34: 0.12452542 | N34: =M34*L34 -> 0.37357627 | Q34: =M34+0.003 -> 0.12752542 | R34: =VLOOKUP(B34,#REF!,13,0) -> #REF! | S34: =R34*L34 -> #REF! | T34: =M34+0.018415205 -> 0.14294063 | U34: =VLOOKUP(B34,'SOLVER NOVO'!A:E,5,) -> 9.1533296 | V34: =M34+0.017525424 -> 0.14205085
A35: 3744887 | B35: P6200 | C35: 6114.30.30.30 | D35: 00BC01 | E35: Of man-made fibres | F35: Sense Slim BT Bra | J35: 2 | L35: =SUM(G35:K35) -> 2 | M35: 0.10252542 | N35: =M35*L35 -> 0.20505085 | V35: =M35+0.017525424 -> 0.12005085
A36: 3744887 | B36: P1154 | C36: 6106.20.10.10 | D36: 00RX80 | E36: Of man-made fibres | F36: LIVE Comfort Tank Top | J36: 2 | K36: 1 | L36: =SUM(G36:K36) -> 3 | M36: 0.12052542 | N36: =M36*L36 -> 0.36157627 | V36: =M36+0.017525424 -> 0.13805085
A37: 3744887 | B37: P1222 | C37: 6114.30.30.30 | D37: 00BC14 | E37: Of man-made fibres | F37: LIVE Move Bra | J37: 2 | L37: =SUM(G37:K37) -> 2 | M37: 0.11252542 | N37: =M37*L37 -> 0.22505085 | V37: =M37+0.017525424 -> 0.13005085
A38: 3744887 | B38: P1437 | C38: 6114.30.30.30 | D38: 00BC14 | E38: Of man-made fibres | F38: LIVE Short Bodysuit | H38: 3 | J38: 1 | L38: =SUM(G38:K38) -> 4 | M38: 0.15252542 | N38: =M38*L38 -> 0.6101017 | V38: =M38+0.017525424 -> 0.17005085
A39: 3744887 | B39: P1479 | C39: 6104.63.10.20 | D39: 00BC14 | E39: Of synthetic fibres | F39: LIVE Fit Short | I39: 2 | L39: =SUM(G39:K39) -> 2 | M39: 0.13752542 | N39: =M39*L39 -> 0.27505085 | V39: =M39+0.017525424 -> 0.15505085
A40: 3744887 | B40: P1497 | C40: 6104.63.10.20 | D40: 00BC01 | E40: Of synthetic fibres | F40: Maxi LIVE Short | H40: 10 | L40: =SUM(G40:K40) -> 10 | M40: 0.11752542 | N40: =M40*L40 -> 1.1752542 | V40: =M40+0.017525424 -> 0.13505085
A41: 3744887 | B41: P1499 | C41: 6202.40.15.10 | D41: 00BC01 | E41: Of synthetic fibres | F41: Maxi LIVE Jacket | J41: 4 | L41: =SUM(G41:K41) -> 4 | M41: 0.30252542 | N41: =M41*L41 -> 1.2101017 | V41: =M41+0.017525424 -> 0.32005085
A42: 3744887 | B42: P1560 | C42: 6114.30.30.30 | D42: 00BC01 | E42: Of man-made fibres | F42: Reversible LIVE Multi Bra | J42: 1 | L42: =SUM(G42:K42) -> 1 | M42: 0.11752542 | N42: =M42*L42 -> 0.11752542 | V42: =M42+0.017525424 -> 0.13505085
A43: 3744887 | B43: P1560 | C43: 6114.30.30.30 | D43: 0AZ190 | E43: Of man-made fibres | F43: Reversible LIVE Multi Bra | I43: 2 | L43: =SUM(G43:K43) -> 2 | M43: 0.092525424 | N43: =M43*L43 -> 0.18505085 | V43: =M43+0.017525424 -> 0.11005085
A44: 3744887 | B44: P1581 | C44: 6104.63.10.20 | D44: 00BC01 | E44: Of synthetic fibres | F44: Allure Adaptiv Fit Shorts | J44: 2 | L44: =SUM(G44:K44) -> 2 | M44: 0.14752542 | N44: =M44*L44 -> 0.29505085 | V44: =M44+0.017525424 -> 0.16505085
A45: 3744887 | B45: P1589 | C45: 6114.30.30.30 | D45: 00BC14 | E45: Of man-made fibres | F45: Top LIVE Icon | H45: 3 | J45: 2 | L45: =SUM(G45:K45) -> 5 | M45: 0.10652542 | N45: =M45*L45 -> 0.53262712 | V45: =M45+0.017525424 -> 0.12405085
A46: 3744887 | B46: P1590 | C46: 6104.63.10.20 | D46: 00BC14 | E46: Of synthetic fibres | F46: LIVE Icon Fit Short | K46: 1 | L46: =SUM(G46:K46) -> 1 | M46: 0.15752542 | N46: =M46*L46 -> 0.15752542 | V46: =M46+0.017525424 -> 0.17505085
A47: 3744887 | B47: P1596 | C47: 6104.63.10.20 | D47: 00BC01 | E47: Of synthetic fibres | F47: Maxi LIVE Leggings | H47: 3 | L47: =SUM(G47:K47) -> 3 | M47: 0.11752542 | N47: =M47*L47 -> 0.35257627 | V47: =M47+0.017525424 -> 0.13505085
A48: 3744887 | B48: P1601 | C48: 6102.20.00.10 | D48: 00BC01 | E48: Of cotton | F48: Welfare Hoodie | H48: 2 | L48: =SUM(G48:K48) -> 2 | M48: 0.28752542 | N48: =M48*L48 -> 0.57505085 | V48: =M48+0.017525424 -> 0.30505085
A49: 3744887 | B49: P1602 | C49: 6104.62.10.20 | D49: 00BC01 | E49: Of cotton | F49: Welfare Short | G49: 2 | J49: 1 | L49: =SUM(G49:K49) -> 3 | M49: 0.13252542 | N49: =M49*L49 -> 0.39757627 | V49: =M49+0.017525424 -> 0.15005085
A50: 3744887 | B50: P1603 | C50: 6104.62.10.20 | D50: 00BC01 | E50: Of cotton | F50: Welfare Jogger Pant | G50: 3 | I50: 2 | L50: =SUM(G50:K50) -> 5 | M50: 0.23352542 | N50: =M50*L50 -> 1.1676271 | V50: =M50+0.017525424 -> 0.25105085
A51: 3744887 | B51: P1628 | C51: 6102.30.20.10 | D51: 0AZ190 | E51: Of man-made fibres | F51: Harmony Jacket Pro | J51: 1 | L51: =SUM(G51:K51) -> 1 | M51: 0.27252542 | N51: =M51*L51 -> 0.27252542 | V51: =M51+0.017525424 -> 0.29005085
A52: 3744887 | B52: P1629 | C52: 6114.30.30.30 | D52: 0AZ190 | E52: Of man-made fibres | F52: Speed Bra | G52: 2 | H52: 3 | L52: =SUM(G52:K52) -> 5 | M52: 0.10052542 | N52: =M52*L52 -> 0.50262712 | V52: =M52+0.017525424 -> 0.11805085
A53: 3744887 | B53: P1666 | C53: 6114.30.30.30 | D53: 00BC01 | E53: Of man-made fibres | F53: Sense Motion Slim Bra | H53: 4 | L53: =SUM(G53:K53) -> 4 | M53: 0.097525424 | N53: =M53*L53 -> 0.3901017 | V53: =M53+0.017525424 -> 0.11505085
A54: 3744887 | B54: P1927 | C54: 6106.20.10.10 | D54: 00BC01 | E54: Of man-made fibres | F54: Sense Move Crop Tank | J54: 3 | L54: =SUM(G54:K54) -> 3 | M54: 0.10752542 | N54: =M54*L54 -> 0.32257627 | V54: =M54+0.017525424 -> 0.12505085
A55: 3744887 | B55: P1153 | C55: 6109.90.80.10 | D55: 0AZ190 | E55: Of other textile materials | F55: LIVE Comfort TShirt | J55: 1 | L55: =SUM(G55:K55) -> 1 | M55: 0.12752542 | N55: =M55*L55 -> 0.12752542 | V55: =M55+0.017525424 -> 0.14505085
A56: 3745328 | B56: 46591 | C56: 6104.63.10.20 | D56: 00RX80 | E56: Of synthetic fibres | F56: Seamless Mesh Full Legging | I56: 2 | L56: =SUM(G56:K56) -> 2 | M56: 0.36752542 | N56: =M56*L56 -> 0.73505085 | V56: =M56+0.017525424 -> 0.38505085
A57: 3745328 | B57: 46592 | C57: 6114.30.30.30 | D57: 00RX80 | E57: Of man-made fibres | F57: Seamless Knit Short Bodysuit | G57: 1 | L57: =SUM(G57:K57) -> 1 | M57: 0.23252542 | N57: =M57*L57 -> 0.23252542 | V57: =M57+0.017525424 -> 0.25005085
A58: 3745328 | B58: P0063 | C58: 6114.30.30.30 | D58: 00BC14 | E58: Of man-made fibres | F58: LIVE Curve Bra | H58: 3 | L58: =SUM(G58:K58) -> 3 | M58: 0.082525424 | N58: =M58*L58 -> 0.24757627 | V58: =M58+0.017525424 -> 0.10005085
A59: 3745328 | B59: P1153 | C59: 6109.90.80.10 | D59: 00BC14 | E59: Of other textile materials | F59: LIVE Comfort TShirt | G59: 1 | H59: 3 | I59: 1 | L59: =SUM(G59:K59) -> 5 | M59: 0.10752542 | N59: =M59*L59 -> 0.53762712 | V59: =M59+0.017525424 -> 0.12505085
A60: 3745328 | B60: P1153 | C60: 6109.90.80.10 | D60: 00RX80 | E60: Of other textile materials | F60: LIVE Comfort TShirt | J60: 2 | L60: =SUM(G60:K60) -> 2 | M60: 0.12752542 | N60: =M60*L60 -> 0.25505085 | V60: =M60+0.017525424 -> 0.14505085
A61: 3745328 | B61: P1153 | C61: 6109.90.80.10 | D61: 0AZ190 | E61: Of other textile materials | F61: LIVE Comfort TShirt | G61: 1 | H61: 1 | L61: =SUM(G61:K61) -> 2 | M61: 0.10252542 | N61: =M61*L61 -> 0.20505085 | V61: =M61+0.017525424 -> 0.12005085
A62: 3745328 | B62: P1213 | C62: 6106.20.10.10 | D62: 00BC14 | E62: Of man-made fibres | F62: LIVE Comfort Crop Tank | K62: 1 | L62: =SUM(G62:K62) -> 1 | M62: 0.097525424 | N62: =M62*L62 -> 0.097525424 | V62: =M62+0.017525424 -> 0.11505085
A63: 3745328 | B63: P1213 | C63: 6106.20.10.10 | D63: 00RX80 | E63: Of man-made fibres | F63: LIVE Comfort Crop Tank | K63: 1 | L63: =SUM(G63:K63) -> 1 | M63: 0.097525424 | N63: =M63*L63 -> 0.097525424 | V63: =M63+0.017525424 -> 0.11505085
A64: 3745328 | B64: P1226 | C64: 6104.63.10.20 | D64: 00RX80 | E64: Of synthetic fibres | F64: LIVE Icon Neo Full Legging | H64: 3 | L64: =SUM(G64:K64) -> 3 | M64: 0.21752542 | N64: =M64*L64 -> 0.65257627 | V64: =M64+0.017525424 -> 0.23505085
A65: 3745328 | B65: P1434 | C65: 6114.30.30.30 | D65: 00RX80 | E65: Of man-made fibres | F65: Sense Curve Bra | G65: 1 | I65: 3 | L65: =SUM(G65:K65) -> 4 | M65: 0.085525424 | N65: =M65*L65 -> 0.3421017 | V65: =M65+0.017525424 -> 0.10305085
A66: 3745328 | B66: P1472 | C66: 6104.63.10.20 | D66: 00BC14 | E66: Of synthetic fibres | F66: LIVE Full Length Legging | H66: 3 | J66: 2 | L66: =SUM(G66:K66) -> 5 | M66: 0.23352542 | N66: =M66*L66 -> 1.1676271 | V66: =M66+0.017525424 -> 0.25105085
A67: 3745328 | B67: P1497 | C67: 6104.63.10.20 | D67: 00BC01 | E67: Of synthetic fibres | F67: Maxi LIVE Short | K67: 1 | L67: =SUM(G67:K67) -> 1 | M67: 0.14752542 | N67: =M67*L67 -> 0.14752542 | V67: =M67+0.017525424 -> 0.16505085
A68: 3745328 | B68: P1498 | C68: 6104.63.10.20 | D68: 0AZ190 | E68: Of synthetic fibres | F68: Maxi LIVE Leggings | J68: 1 | L68: =SUM(G68:K68) -> 1 | M68: 0.23752542 | N68: =M68*L68 -> 0.23752542 | V68: =M68+0.017525424 -> 0.25505085
A69: 3745328 | B69: P1559 | C69: 6104.63.10.20 | D69: 0AZ190 | E69: Of synthetic fibres | F69: Hydefit Adaptiv Legging | J69: 2 | K69: 1 | L69: =SUM(G69:K69) -> 3 | M69: 0.24452542 | N69: =M69*L69 -> 0.73357627 | V69: =M69+0.017525424 -> 0.26205085
A70: 3745328 | B70: P1581 | C70: 6104.63.10.20 | D70: 00BC01 | E70: Of synthetic fibres | F70: Allure Adaptiv Fit Shorts | I70: 3 | L70: =SUM(G70:K70) -> 3 | M70: 0.13752542 | N70: =M70*L70 -> 0.41257627 | V70: =M70+0.017525424 -> 0.15505085
A71: 3745328 | B71: P1589 | C71: 6114.30.30.30 | D71: 00BC14 | E71: Of man-made fibres | F71: Top LIVE Icon | K71: 1 | L71: =SUM(G71:K71) -> 1 | M71: 0.11752542 | N71: =M71*L71 -> 0.11752542 | V71: =M71+0.017525424 -> 0.13505085
A72: 3745328 | B72: P1590 | C72: 6104.63.10.20 | D72: 00BC14 | E72: Of synthetic fibres | F72: LIVE Icon Fit Short | J72: 2 | L72: =SUM(G72:K72) -> 2 | M72: 0.14752542 | N72: =M72*L72 -> 0.29505085 | V72: =M72+0.017525424 -> 0.16505085
A73: 3745328 | B73: P1591 | C73: 6104.63.10.20 | D73: 00BC14 | E73: Of synthetic fibres | F73: LIVE Icon Legging | H73: 2 | I73: 2 | K73: 1 | L73: =SUM(G73:K73) -> 5 | M73: 0.23752542 | N73: =M73*L73 -> 1.1876271 | V73: =M73+0.017525424 -> 0.25505085
A74: 3745328 | B74: P1593 | C74: 6109.90.80.10 | D74: 00BC01 | E74: Of other textile materials | F74: Thermo Skin LS T Shirt | J74: 2 | L74: =SUM(G74:K74) -> 2 | M74: 0.15752542 | N74: =M74*L74 -> 0.31505085 | V74: =M74+0.017525424 -> 0.17505085
A75: 3745328 | B75: P1596 | C75: 6104.63.10.20 | D75: 00BC01 | E75: Of synthetic fibres | F75: Maxi LIVE Leggings | H75: 5 | K75: 2 | L75: =SUM(G75:K75) -> 7 | M75: 0.13452542 | N75: =M75*L75 -> 0.94167797 | V75: =M75+0.017525424 -> 0.15205085
A76: 3745328 | B76: P1601 | C76: 6102.20.00.10 | D76: 00BC01 | E76: Of cotton | F76: Welfare Hoodie | H76: 1 | I76: 2 | J76: 1 | L76: =SUM(G76:K76) -> 4 | M76: 0.30752542 | N76: =M76*L76 -> 1.2301017 | V76: =M76+0.017525424 -> 0.32505085
A77: 3745328 | B77: P1603 | C77: 6104.62.10.20 | D77: 00BC01 | E77: Of cotton | F77: Welfare Jogger Pant | H77: 1 | L77: =SUM(G77:K77) -> 1 | M77: 0.23752542 | N77: =M77*L77 -> 0.23752542 | V77: =M77+0.017525424 -> 0.25505085
A78: 3745328 | B78: P1628 | C78: 6102.30.20.10 | D78: 0AZ190 | E78: Of man-made fibres | F78: Harmony Jacket Pro | G78: 1 | L78: =SUM(G78:K78) -> 1 | M78: 0.13752542 | N78: =M78*L78 -> 0.13752542 | V78: =M78+0.017525424 -> 0.15505085
A79: 3745328 | B79: P1629 | C79: 6114.30.30.30 | D79: 0AZ190 | E79: Of man-made fibres | F79: Speed Bra | I79: 2 | J79: 2 | L79: =SUM(G79:K79) -> 4 | M79: 0.11052542 | N79: =M79*L79 -> 0.4421017 | V79: =M79+0.017525424 -> 0.12805085
A80: 3745328 | B80: P1666 | C80: 6114.30.30.30 | D80: 00BC01 | E80: Of man-made fibres | F80: Sense Motion Slim Bra | G80: 1 | L80: =SUM(G80:K80) -> 1 | M80: 0.092525424 | N80: =M80*L80 -> 0.092525424 | V80: =M80+0.017525424 -> 0.11005085
A81: 3745328 | B81: P1927 | C81: 6106.20.10.10 | D81: 00BC01 | E81: Of man-made fibres | F81: Sense Move Crop Tank | G81: 3 | H81: 5 | L81: =SUM(G81:K81) -> 8 | M81: 0.10452542 | N81: =M81*L81 -> 0.83620339 | V81: =M81+0.017525424 -> 0.12205085
A82: 3745328 | B82: P6200 | C82: 6114.30.30.30 | D82: 00BC01 | E82: Of man-made fibres | F82: Sense Slim BT Bra | H82: 3 | L82: =SUM(G82:K82) -> 3 | M82: 0.092525424 | N82: =M82*L82 -> 0.27757627 | V82: =M82+0.017525424 -> 0.11005085
A83: 3745328 | B83: P6200 | C83: 6114.30.30.30 | D83: 00RX80 | E83: Of man-made fibres | F83: Sense Slim BT Bra | G83: 1 | I83: 3 | J83: 2 | L83: =SUM(G83:K83) -> 6 | M83: 0.097525424 | N83: =M83*L83 -> 0.58515254 | V83: =M83+0.017525424 -> 0.11505085
A84: 3745654 | B84: 46586 | C84: 6114.30.30.30 | D84: 00RX80 | E84: Of man-made fibres | F84: Melt Square Bra | I84: 3 | J84: 2 | L84: =SUM(G84:K84) -> 5 | M84: 0.10452542 | N84: =M84*L84 -> 0.52262712 | V84: =M84+0.017525424 -> 0.12205085
A85: 3745654 | B85: P1603 | C85: 6104.62.10.20 | D85: 00BC01 | E85: Of cotton | F85: Welfare Jogger Pant | J85: 1 | L85: =SUM(G85:K85) -> 1 | M85: 0.27752542 | N85: =M85*L85 -> 0.27752542 | V85: =M85+0.017525424 -> 0.29505085
A86: 3745654 | B86: 46589 | C86: 6104.63.10.20 | D86: 00RX80 | E86: Of synthetic fibres | F86: Square Melt Ballerina Pants | H86: 2 | L86: =SUM(G86:K86) -> 2 | M86: 0.24252542 | N86: =M86*L86 -> 0.48505085 | V86: =M86+0.017525424 -> 0.26005085
A87: 3745654 | B87: 46591 | C87: 6104.63.10.20 | D87: 00RX80 | E87: Of synthetic fibres | F87: Seamless Mesh Full Legging | H87: 2 | L87: =SUM(G87:K87) -> 2 | M87: 0.23752542 | N87: =M87*L87 -> 0.47505085 | V87: =M87+0.017525424 -> 0.25505085
A88: 3745654 | B88: 46592 | C88: 6114.30.30.30 | D88: 00RX80 | E88: Of man-made fibres | F88: Seamless Knit Short Bodysuit | H88: 3 | L88: =SUM(G88:K88) -> 3 | M88: 0.14752542 | N88: =M88*L88 -> 0.44257627 | V88: =M88+0.017525424 -> 0.16505085
A89: 3745654 | B89: P0063 | C89: 6114.30.30.30 | D89: 00BC14 | E89: Of man-made fibres | F89: LIVE Curve Bra | G89: 1 | K89: 1 | L89: =SUM(G89:K89) -> 2 | M89: 0.087525424 | N89: =M89*L89 -> 0.17505085 | V89: =M89+0.017525424 -> 0.10505085
A90: 3745654 | B90: P1153 | C90: 6109.90.80.10 | D90: 00BC14 | E90: Of other textile materials | F90: LIVE Comfort TShirt | J90: 1 | L90: =SUM(G90:K90) -> 1 | M90: 0.12752542 | N90: =M90*L90 -> 0.12752542 | V90: =M90+0.017525424 -> 0.14505085
A91: 3745654 | B91: P1153 | C91: 6109.90.80.10 | D91: 00RX80 | E91: Of other textile materials | F91: LIVE Comfort TShirt | H91: 3 | L91: =SUM(G91:K91) -> 3 | M91: 0.10752542 | N91: =M91*L91 -> 0.32257627 | V91: =M91+0.017525424 -> 0.12505085
A92: 3745654 | B92: P1153 | C92: 6109.90.80.10 | D92: 0AZ190 | E92: Of other textile materials | F92: LIVE Comfort TShirt | H92: 1 | L92: =SUM(G92:K92) -> 1 | M92: 0.10752542 | N92: =M92*L92 -> 0.10752542 | V92: =M92+0.017525424 -> 0.12505085
A93: 3745654 | B93: P1154 | C93: 6106.20.10.10 | D93: 00BC14 | E93: Of man-made fibres | F93: LIVE Comfort Tank Top | H93: 3 | L93: =SUM(G93:K93) -> 3 | M93: 0.097525424 | N93: =M93*L93 -> 0.29257627 | V93: =M93+0.017525424 -> 0.11505085
A94: 3745654 | B94: P1213 | C94: 6106.20.10.10 | D94: 00BC14 | E94: Of man-made fibres | F94: LIVE Comfort Crop Tank | H94: 2 | I94: 2 | L94: =SUM(G94:K94) -> 4 | M94: 0.072525424 | N94: =M94*L94 -> 0.2901017 | V94: =M94+0.017525424 -> 0.090050848
A95: 3745654 | B95: P1213 | C95: 6106.20.10.10 | D95: 00RX80 | E95: Of man-made fibres | F95: LIVE Comfort Crop Tank | I95: 2 | L95: =SUM(G95:K95) -> 2 | M95: 0.077525424 | N95: =M95*L95 -> 0.15505085 | V95: =M95+0.017525424 -> 0.095050848
A96: 3745654 | B96: P1222 | C96: 6114.30.30.30 | D96: 00BC14 | E96: Of man-made fibres | F96: LIVE Move Bra | I96: 3 | L96: =SUM(G96:K96) -> 3 | M96: 0.10752542 | N96: =M96*L96 -> 0.32257627 | V96: =M96+0.017525424 -> 0.12505085
A97: 3745654 | B97: P1225 | C97: 6104.63.10.20 | D97: 00RX80 | E97: Of synthetic fibres | F97: LIVE Icon Neo Short | I97: 3 | L97: =SUM(G97:K97) -> 3 | M97: 0.13752542 | N97: =M97*L97 -> 0.41257627 | V97: =M97+0.017525424 -> 0.15505085
A98: 3745654 | B98: P1226 | C98: 6104.63.10.20 | D98: 00RX80 | E98: Of synthetic fibres | F98: LIVE Icon Neo Full Legging | I98: 2 | L98: =SUM(G98:K98) -> 2 | M98: 0.23752542 | N98: =M98*L98 -> 0.47505085 | V98: =M98+0.017525424 -> 0.25505085
A99: 3745654 | B99: P1298 | C99: 6114.30.30.30 | D99: 00RX80 | E99: Of man-made fibres | F99: LIVE Icon Neo Bra | H99: 3 | I99: 2 | J99: 1 | L99: =SUM(G99:K99) -> 6 | M99: 0.10552542 | N99: =M99*L99 -> 0.63315254 | V99: =M99+0.017525424 -> 0.12305085
A100: 3745654 | B100: P1434 | C100: 6114.30.30.30 | D100: 00RX80 | E100: Of man-made fibres | F100: Sense Curve Bra | H100: 3 | J100: 2 | K100: 1 | L100: =SUM(G100:K100) -> 6 | M100: 0.088525424 | N100: =M100*L100 -> 0.53115254 | V100: =M100+0.017525424 -> 0.10605085
A101: 3745654 | B101: P1437 | C101: 6114.30.30.30 | D101: 00BC14 | E101: Of man-made fibres | F101: LIVE Short Bodysuit | I101: 2 | L101: =SUM(G101:K101) -> 2 | M101: 0.15752542 | N101: =M101*L101 -> 0.31505085 | V101: =M101+0.017525424 -> 0.17505085
A102: 3745654 | B102: P1472 | C102: 6104.63.10.20 | D102: 00BC14 | E102: Of synthetic fibres | F102: LIVE Full Length Legging | I102: 3 | L102: =SUM(G102:K102) -> 3 | M102: 0.23752542 | N102: =M102*L102 -> 0.71257627 | V102: =M102+0.017525424 -> 0.25505085
...

Sheet packing
A1: Order | B1: BOX | C1: Reference | D1: N.C.M. | E1: Color | F1: Product Materials | G1: Description | H1: XS | I1: S | J1: M | K1: L | L1: XL | M1: Unit Weight
A2: 2799646 | B2: 3744887 | C2: P1153 | D2: 6109.90.80.10 | E2: 00BC14 | F2: Of other textile materials | G2: LIVE Comfort TShirt | J2: 2 | L2: 1 | M2: 0.107
A3: 2799646 | B3: 3744887 | C3: P6200 | D3: 6114.30.30.30 | E3: 00BC01 | F3: Of man-made fibres | G3: Sense Slim BT Bra | K3: 2 | M3: 0.085
A4: 2799646 | B4: 3744887 | C4: P1154 | D4: 6106.20.10.10 | E4: 00RX80 | F4: Of man-made fibres | G4: LIVE Comfort Tank Top | K4: 2 | L4: 1 | M4: 0.103
A5: 2799646 | B5: 3744887 | C5: P1222 | D5: 6114.30.30.30 | E5: 00BC14 | F5: Of man-made fibres | G5: LIVE Move Bra | K5: 2 | M5: 0.095
A6: 2799646 | B6: 3744887 | C6: P1437 | D6: 6114.30.30.30 | E6: 00BC14 | F6: Of man-made fibres | G6: LIVE Short Bodysuit | I6: 3 | K6: 1 | M6: 0.135
A7: 2799646 | B7: 3744887 | C7: P1479 | D7: 6104.63.10.20 | E7: 00BC14 | F7: Of synthetic fibres | G7: LIVE Fit Short | J7: 2 | M7: 0.12
A8: 2799646 | B8: 3744887 | C8: P1497 | D8: 6104.63.10.20 | E8: 00BC01 | F8: Of synthetic fibres | G8: Maxi LIVE Short | I8: 10 | M8: 0.1
A9: 2799646 | B9: 3744887 | C9: P1499 | D9: 6202.40.15.10 | E9: 00BC01 | F9: Of synthetic fibres | G9: Maxi LIVE Jacket | K9: 4 | M9: 0.285
A10: 2799646 | B10: 3744887 | C10: P1560 | D10: 6114.30.30.30 | E10: 00BC01 | F10: Of man-made fibres | G10: Reversible LIVE Multi Bra | K10: 1 | M10: 0.1
A11: 2799646 | B11: 3744887 | C11: P1560 | D11: 6114.30.30.30 | E11: 0AZ190 | F11: Of man-made fibres | G11: Reversible LIVE Multi Bra | J11: 2 | M11: 0.075
A12: 2799646 | B12: 3744887 | C12: P1581 | D12: 6104.63.10.20 | E12: 00BC01 | F12: Of synthetic fibres | G12: Allure Adaptiv Fit Shorts | K12: 2 | M12: 0.13
A13: 2799646 | B13: 3744887 | C13: P1589 | D13: 6114.30.30.30 | E13: 00BC14 | F13: Of man-made fibres | G13: Top LIVE Icon | I13: 3 | K13: 2 | M13: 0.089
A14: 2799646 | B14: 3744887 | C14: P1590 | D14: 6104.63.10.20 | E14: 00BC14 | F14: Of synthetic fibres | G14: LIVE Icon Fit Short | L14: 1 | M14: 0.14
A15: 2799646 | B15: 3744887 | C15: P1596 | D15: 6104.63.10.20 | E15: 00BC01 | F15: Of synthetic fibres | G15: Maxi LIVE Leggings | I15: 3 | M15: 0.1
A16: 2799646 | B16: 3744887 | C16: P1601 | D16: 6102.20.00.10 | E16: 00BC01 | F16: Of cotton | G16: Welfare Hoodie | I16: 2 | M16: 0.27
A17: 2799646 | B17: 3744887 | C17: P1602 | D17: 6104.62.10.20 | E17: 00BC01 | F17: Of cotton | G17: Welfare Short | H17: 2 | K17: 1 | M17: 0.115
A18: 2799646 | B18: 3744887 | C18: P1603 | D18: 6104.62.10.20 | E18: 00BC01 | F18: Of cotton | G18: Welfare Jogger Pant | H18: 3 | J18: 2 | M18: 0.216
A19: 2799646 | B19: 3744887 | C19: P1628 | D19: 6102.30.20.10 | E19: 0AZ190 | F19: Of man-made fibres | G19: Harmony Jacket Pro | K19: 1 | M19: 0.255
A20: 2799646 | B20: 3744887 | C20: P1629 | D20: 6114.30.30.30 | E20: 0AZ190 | F20: Of man-made fibres | G20: Speed Bra | H20: 2 | I20: 3 | M20: 0.083
A21: 2799646 | B21: 3744887 | C21: P1666 | D21: 6114.30.30.30 | E21: 00BC01 | F21: Of man-made fibres | G21: Sense Motion Slim Bra | I21: 4 | M21: 0.08
A22: 2799646 | B22: 3744887 | C22: P1927 | D22: 6106.20.10.10 | E22: 00BC01 | F22: Of man-made fibres | G22: Sense Move Crop Tank | K22: 3 | M22: 0.09
A23: 2799646 | B23: 3744887 | C23: P1153 | D23: 6109.90.80.10 | E23: 0AZ190 | F23: Of other textile materials | G23: LIVE Comfort TShirt | K23: 1 | M23: 0.11
A24: 2799646 | B24: 3745328 | C24: 46591 | D24: 6104.63.10.20 | E24: 00RX80 | F24: Of synthetic fibres | G24: Seamless Mesh Full Legging | J24: 2 | M24: 0.35
A25: 2799646 | B25: 3745328 | C25: 46592 | D25: 6114.30.30.30 | E25: 00RX80 | F25: Of man-made fibres | G25: Seamless Knit Short Bodysuit | H25: 1 | M25: 0.215
A26: 2799646 | B26: 3745328 | C26: P0063 | D26: 6114.30.30.30 | E26: 00BC14 | F26: Of man-made fibres | G26: LIVE Curve Bra | I26: 3 | M26: 0.065
A27: 2799646 | B27: 3745328 | C27: P1153 | D27: 6109.90.80.10 | E27: 00BC14 | F27: Of other textile materials | G27: LIVE Comfort TShirt | H27: 1 | I27: 3 | J27: 1 | M27: 0.09
A28: 2799646 | B28: 3745328 | C28: P1153 | D28: 6109.90.80.10 | E28: 00RX80 | F28: Of other textile materials | G28: LIVE Comfort TShirt | K28: 2 | M28: 0.11
A29: 2799646 | B29: 3745328 | C29: P1153 | D29: 6109.90.80.10 | E29: 0AZ190 | F29: Of other textile materials | G29: LIVE Comfort TShirt | H29: 1 | I29: 1 | M29: 0.085
A30: 2799646 | B30: 3745328 | C30: P1213 | D30: 6106.20.10.10 | E30: 00BC14 | F30: Of man-made fibres | G30: LIVE Comfort Crop Tank | L30: 1 | M30: 0.08
A31: 2799646 | B31: 3745328 | C31: P1213 | D31: 6106.20.10.10 | E31: 00RX80 | F31: Of man-made fibres | G31: LIVE Comfort Crop Tank | L31: 1 | M31: 0.08
A32: 2799646 | B32: 3745328 | C32: P1226 | D32: 6104.63.10.20 | E32: 00RX80 | F32: Of synthetic fibres | G32: LIVE Icon Neo Full Legging | I32: 3 | M32: 0.2
A33: 2799646 | B33: 3745328 | C33: P1434 | D33: 6114.30.30.30 | E33: 00RX80 | F33: Of man-made fibres | G33: Sense Curve Bra | H33: 1 | J33: 3 | M33: 0.068
A34: 2799646 | B34: 3745328 | C34: P1472 | D34: 6104.63.10.20 | E34: 00BC14 | F34: Of synthetic fibres | G34: LIVE Full Length Legging | I34: 3 | K34: 2 | M34: 0.216
A35: 2799646 | B35: 3745328 | C35: P1497 | D35: 6104.63.10.20 | E35: 00BC01 | F35: Of synthetic fibres | G35: Maxi LIVE Short | L35: 1 | M35: 0.13
A36: 2799646 | B36: 3745328 | C36: P1498 | D36: 6104.63.10.20 | E36: 0AZ190 | F36: Of synthetic fibres | G36: Maxi LIVE Leggings | K36: 1 | M36: 0.22
A37: 2799646 | B37: 3745328 | C37: P1559 | D37: 6104.63.10.20 | E37: 0AZ190 | F37: Of synthetic fibres | G37: Hydefit Adaptiv Legging | K37: 2 | L37: 1 | M37: 0.227
A38: 2799646 | B38: 3745328 | C38: P1581 | D38: 6104.63.10.20 | E38: 00BC01 | F38: Of synthetic fibres | G38: Allure Adaptiv Fit Shorts | J38: 3 | M38: 0.12
A39: 2799646 | B39: 3745328 | C39: P1589 | D39: 6114.30.30.30 | E39: 00BC14 | F39: Of man-made fibres | G39: Top LIVE Icon | L39: 1 | M39: 0.1
A40: 2799646 | B40: 3745328 | C40: P1590 | D40: 6104.63.10.20 | E40: 00BC14 | F40: Of synthetic fibres | G40: LIVE Icon Fit Short | K40: 2 | M40: 0.13
A41: 2799646 | B41: 3745328 | C41: P1591 | D41: 6104.63.10.20 | E41: 00BC14 | F41: Of synthetic fibres | G41: LIVE Icon Legging | I41: 2 | J41: 2 | L41: 1 | M41: 0.22
A42: 2799646 | B42: 3745328 | C42: P1593 | D42: 6109.90.80.10 | E42: 00BC01 | F42: Of other textile materials | G42: Thermo Skin LS T Shirt | K42: 2 | M42: 0.14
A43: 2799646 | B43: 3745328 | C43: P1596 | D43: 6104.63.10.20 | E43: 00BC01 | F43: Of synthetic fibres | G43: Maxi LIVE Leggings | I43: 5 | L43: 2 | M43: 0.117
A44: 2799646 | B44: 3745328 | C44: P1601 | D44: 6102.20.00.10 | E44: 00BC01 | F44: Of cotton | G44: Welfare Hoodie | I44: 1 | J44: 2 | K44: 1 | M44: 0.29
A45: 2799646 | B45: 3745328 | C45: P1603 | D45: 6104.62.10.20 | E45: 00BC01 | F45: Of cotton | G45: Welfare Jogger Pant | I45: 1 | M45: 0.22
A46: 2799646 | B46: 3745328 | C46: P1628 | D46: 6102.30.20.10 | E46: 0AZ190 | F46: Of man-made fibres | G46: Harmony Jacket Pro | H46: 1 | M46: 0.12
A47: 2799646 | B47: 3745328 | C47: P1629 | D47: 6114.30.30.30 | E47: 0AZ190 | F47: Of man-made fibres | G47: Speed Bra | J47: 2 | K47: 2 | M47: 0.093
A48: 2799646 | B48: 3745328 | C48: P1666 | D48: 6114.30.30.30 | E48: 00BC01 | F48: Of man-made fibres | G48: Sense Motion Slim Bra | H48: 1 | M48: 0.075
A49: 2799646 | B49: 3745328 | C49: P1927 | D49: 6106.20.10.10 | E49: 00BC01 | F49: Of man-made fibres | G49: Sense Move Crop Tank | H49: 3 | I49: 5 | M49: 0.087
A50: 2799646 | B50: 3745328 | C50: P6200 | D50: 6114.30.30.30 | E50: 00BC01 | F50: Of man-made fibres | G50: Sense Slim BT Bra | I50: 3 | M50: 0.075
A51: 2799646 | B51: 3745328 | C51: P6200 | D51: 6114.30.30.30 | E51: 00RX80 | F51: Of man-made fibres | G51: Sense Slim BT Bra | H51: 1 | J51: 3 | K51: 2 | M51: 0.08
A52: 2799646 | B52: 3745654 | C52: 46586 | D52: 6114.30.30.30 | E52: 00RX80 | F52: Of man-made fibres | G52: Melt Square Bra | J52: 3 | K52: 2 | M52: 0.087
A53: 2799646 | B53: 3745654 | C53: P1603 | D53: 6104.62.10.20 | E53: 00BC01 | F53: Of cotton | G53: Welfare Jogger Pant | K53: 1 | M53: 0.26
A54: 2799646 | B54: 3745654 | C54: 46589 | D54: 6104.63.10.20 | E54: 00RX80 | F54: Of synthetic fibres | G54: Square Melt Ballerina Pants | I54: 2 | M54: 0.225
A55: 2799646 | B55: 3745654 | C55: 46591 | D55: 6104.63.10.20 | E55: 00RX80 | F55: Of synthetic fibres | G55: Seamless Mesh Full Legging | I55: 2 | M55: 0.22
A56: 2799646 | B56: 3745654 | C56: 46592 | D56: 6114.30.30.30 | E56: 00RX80 | F56: Of man-made fibres | G56: Seamless Knit Short Bodysuit | I56: 3 | M56: 0.13
A57: 2799646 | B57: 3745654 | C57: P0063 | D57: 6114.30.30.30 | E57: 00BC14 | F57: Of man-made fibres | G57: LIVE Curve Bra | H57: 1 | L57: 1 | M57: 0.07
A58: 2799646 | B58: 3745654 | C58: P1153 | D58: 6109.90.80.10 | E58: 00BC14 | F58: Of other textile materials | G58: LIVE Comfort TShirt | K58: 1 | M58: 0.11
A59: 2799646 | B59: 3745654 | C59: P1153 | D59: 6109.90.80.10 | E59: 00RX80 | F59: Of other textile materials | G59: LIVE Comfort TShirt | I59: 3 | M59: 0.09
A60: 2799646 | B60: 3745654 | C60: P1153 | D60: 6109.90.80.10 | E60: 0AZ190 | F60: Of other textile materials | G60: LIVE Comfort TShirt | I60: 1 | M60: 0.09
A61: 2799646 | B61: 3745654 | C61: P1154 | D61: 6106.20.10.10 | E61: 00BC14 | F61: Of man-made fibres | G61: LIVE Comfort Tank Top | I61: 3 | M61: 0.08
A62: 2799646 | B62: 3745654 | C62: P1213 | D62: 6106.20.10.10 | E62: 00BC14 | F62: Of man-made fibres | G62: LIVE Comfort Crop Tank | I62: 2 | J62: 2 | M62: 0.055
A63: 2799646 | B63: 3745654 | C63: P1213 | D63: 6106.20.10.10 | E63: 00RX80 | F63: Of man-made fibres | G63: LIVE Comfort Crop Tank | J63: 2 | M63: 0.06
A64: 2799646 | B64: 3745654 | C64: P1222 | D64: 6114.30.30.30 | E64: 00BC14 | F64: Of man-made fibres | G64: LIVE Move Bra | J64: 3 | M64: 0.09
A65: 2799646 | B65: 3745654 | C65: P1225 | D65: 6104.63.10.20 | E65: 00RX80 | F65: Of synthetic fibres | G65: LIVE Icon Neo Short | J65: 3 | M65: 0.12
A66: 2799646 | B66: 3745654 | C66: P1226 | D66: 6104.63.10.20 | E66: 00RX80 | F66: Of synthetic fibres | G66: LIVE Icon Neo Full Legging | J66: 2 | M66: 0.22
A67: 2799646 | B67: 3745654 | C67: P1298 | D67: 6114.30.30.30 | E67: 00RX80 | F67: Of man-made fibres | G67: LIVE Icon Neo Bra | I67: 3 | J67: 2 | K67: 1 | M67: 0.088
A68: 2799646 | B68: 3745654 | C68: P1434 | D68: 6114.30.30.30 | E68: 00RX80 | F68: Of man-made fibres | G68: Sense Curve Bra | I68: 3 | K68: 2 | L68: 1 | M68: 0.071
A69: 2799646 | B69: 3745654 | C69: P1437 | D69: 6114.30.30.30 | E69: 00BC14 | F69: Of man-made fibres | G69: LIVE Short Bodysuit | J69: 2 | M69: 0.14
A70: 2799646 | B70: 3745654 | C70: P1472 | D70: 6104.63.10.20 | E70: 00BC14 | F70: Of synthetic fibres | G70: LIVE Full Length Legging | J70: 3 | M70: 0.22
A71: 2799646 | B71: 3745654 | C71: P1479 | D71: 6104.63.10.20 | E71: 00BC14 | F71: Of synthetic fibres | G71: LIVE Fit Short | H71: 1 | M71: 0.1
A72: 2799646 | B72: 3745654 | C72: P1497 | D72: 6104.63.10.20 | E72: 00BC01 | F72: Of synthetic fibres | G72: Maxi LIVE Short | J72: 6 | K72: 4 | M72: 0.114
A73: 2799646 | B73: 3745654 | C73: P1560 | D73: 6114.30.30.30 | E73: 00BC01 | F73: Of man-made fibres | G73: Reversible LIVE Multi Bra | L73: 3 | M73: 0.085
A74: 2799646 | B74: 3745654 | C74: P1581 | D74: 6104.63.10.20 | E74: 00BC01 | F74: Of synthetic fibres | G74: Allure Adaptiv Fit Shorts | I74: 4 | M74: 0.11
A75: 2799646 | B75: 3745654 | C75: P1589 | D75: 6114.30.30.30 | E75: 00BC14 | F75: Of man-made fibres | G75: Top LIVE Icon | J75: 3 | M75: 0.09
A76: 2799646 | B76: 3745654 | C76: P1590 | D76: 6104.63.10.20 | E76: 00BC14 | F76: Of synthetic fibres | G76: LIVE Icon Fit Short | I76: 3 | M76: 0.11
A77: 2799646 | B77: 3745654 | C77: P1593 | D77: 6109.90.80.10 | E77: 00BC01 | F77: Of other textile materials | G77: Thermo Skin LS T Shirt | I77: 3 | M77: 0.12
A78: 2799646 | B78: 3745654 | C78: P1601 | D78: 6102.20.00.10 | E78: 00BC01 | F78: Of cotton | G78: Welfare Hoodie | H78: 3 | M78: 0.25
A79: 2799646 | B79: 3745654 | C79: 46588 | D79: 6104.63.10.20 | E79: 00RX80 | F79: Of synthetic fibres | G79: Melt Square Full Legging | J79: 2 | M79: 0.205

Sheet SOLVER NOVO
A1: REF | B1: NCM | C1: QTY PEÇAS | D1: DOLAR 2019 | E1: VALOR UNIT DOL | F1: VALOR DOL TOTAL | G1: VALOR UNIT REAL
A2: 46586 | B2: 6114.30.00 | C2: 8 | D2: =VLOOKUP(A2,TIMELESS!A:C,3,FALSE) -> 22.78 | E2: 8.6141795 | F2: =E2*C2 -> 68.913436 | G2: =E2*5.1737 -> 44.56718
A3: 46587 | B3: 6104.63.00 | C3: 5 | D3: =VLOOKUP(A3,TIMELESS!A:C,3,FALSE) -> 18.18 | E3: 8.7496168 | F3: =E3*C3 -> 43.748084 | G3: =E3*5.1737 -> 45.267893
A4: 46588 | B4: 6104.63.00 | C4: 6 | D4: =VLOOKUP(A4,TIMELESS!A:C,3,FALSE) -> 27.38 | E4: 10.493706 | F4: =E4*C4 -> 62.962235 | G4: =E4*5.1737 -> 54.291286
A5: 46589 | B5: 6104.63.00 | C5: 5 | D5: =VLOOKUP(A5,TIMELESS!A:C,3,FALSE) -> 34.58 | E5: 9.0113994 | F5: =E5*C5 -> 45.056997 | G5: =E5*5.1737 -> 46.622277
A6: 46590 | B6: 6114.30.00 | C6: 5 | D6: =VLOOKUP(A6,TIMELESS!A:C,3,FALSE) -> 22.78 | E6: 9.7850352 | F6: =E6*C6 -> 48.925176 | G6: =E6*5.1737 -> 50.624837
A7: 46591 | B7: 6104.63.00 | C7: 5 | D7: =VLOOKUP(A7,TIMELESS!A:C,3,FALSE) -> 22.78 | E7: 9.6712217 | F7: =E7*C7 -> 48.356108 | G7: =E7*5.1737 -> 50.036 | J7: =SUM(F2:F166) -> 4055.3476
A8: 46592 | B8: 6114.30.00 | C8: 6 | D8: =VLOOKUP(A8,TIMELESS!A:C,3,FALSE) -> 39.18 | E8: 9.764121 | F8: =E8*C8 -> 58.584726 | G8: =E8*5.1737 -> 50.516633 | J8: =J7*5.1737 -> 20981.152
A9: P0063 | B9: 6114.30.00 | C9: 9 | D9: =VLOOKUP(A9,TIMELESS!A:C,3,FALSE) -> 19.98 | E9: 11.37848 | F9: =E9*C9 -> 102.40632 | G9: =E9*5.1737 -> 58.868842
A10: P1153 | B10: 6109.90.00 | C10: 22 | D10: =VLOOKUP(A10,PULSE!A:C,3,0) -> 18.18 | E10: 9.1533296 | F10: =E10*C10 -> 201.37325 | G10: =E10*5.1737 -> 47.356582
A11: P1154 | B11: 6106.20.00 | C11: 18 | D11: =VLOOKUP(A11,PULSE!A:C,3,0) -> 17.38 | E11: 7.817765 | F11: =E11*C11 -> 140.71977 | G11: =E11*5.1737 -> 40.446771
A12: P1213 | B12: 6106.20.00 | C12: 15 | D12: =VLOOKUP(A12,PULSE!A:C,3,0) -> 15.58 | E12: 8.7312149 | F12: =E12*C12 -> 130.96822 | G12: =E12*5.1737 -> 45.172687
A13: P1222 | B13: 6114.30.00 | C13: 9 | D13: =VLOOKUP(A13,PULSE!A:C,3,0) -> 23.78 | E13: 9.0584904 | F13: =E13*C13 -> 81.526413 | G13: =E13*5.1737 -> 46.865912
A14: P1225 | B14: 6104.63.00 | C14: 6 | D14: =VLOOKUP(A14,PULSE!A:C,3,FALSE) -> 21.98 | E14: 8.7623457 | F14: =E14*C14 -> 52.574074 | G14: =E14*5.1737 -> 45.333748
A15: P1226 | B15: 6104.63.00 | C15: 8 | D15: =VLOOKUP(A15,PULSE!A:C,3,0) -> 29.18 | E15: 10.234378 | F15: =E15*C15 -> 81.875022 | G15: =E15*5.1737 -> 52.9496
A16: P1298 | B16: 6114.30.00 | C16: 6 | D16: =VLOOKUP(A16,PULSE!A:C,3,0) -> 22.78 | E16: 10.644185 | F16: =E16*C16 -> 63.865108 | G16: =E16*5.1737 -> 55.069818
A17: P1434 | B17: 6114.30.00 | C17: 10 | D17: =VLOOKUP(A17,PULSE!A:C,3,0) -> 17.38 | E17: 7.0815216 | F17: =E17*C17 -> 70.815216 | G17: =E17*5.1737 -> 36.637668
A18: P1437 | B18: 6114.30.00 | C18: 6 | D18: =VLOOKUP(A18,PULSE!A:C,3,0) -> 36.38 | E18: 8.7935381 | F18: =E18*C18 -> 52.761229 | G18: =E18*5.1737 -> 45.495128
A19: P1472 | B19: 6104.63.00 | C19: 9 | D19: =VLOOKUP(A19,PULSE!A:C,3,0) -> 29.98 | E19: 6.7037163 | F19: =E19*C19 -> 60.333447 | G19: =E19*5.1737 -> 34.683017
A20: P1479 | B20: 6104.63.00 | C20: 6 | D20: =VLOOKUP(A20,PULSE!A:C,3,0) -> 22.78 | E20: 10.655789 | F20: =E20*C20 -> 63.934734 | G20: =E20*5.1737 -> 55.129855
A21: P1497 | B21: 6104.63.00 | C21: 21 | D21: =VLOOKUP(A21,PULSE!A:C,3,0) -> 21.98 | E21: 9.5763917 | F21: =E21*C21 -> 201.10423 | G21: =E21*5.1737 -> 49.545378
A22: P1498 | B22: 6104.63.00 | C22: 5 | D22: =VLOOKUP(A22,PULSE!A:C,3,0) -> 29.98 | E22: 8.4328336 | F22: =E22*C22 -> 42.164168 | G22: =E22*5.1737 -> 43.628951
A23: P1499 | B23: 6202.40.00 | C23: 21 | D23: =VLOOKUP(A23,PULSE!A:C,3,0) -> 45.58 | E23: 12.359676 | F23: =E23*C23 -> 259.5532 | G23: =E23*5.1737 -> 63.945258
A24: P1559 | B24: 6104.63.00 | C24: 9 | D24: =VLOOKUP(A24,PULSE!A:C,3,0) -> 16.38 | E24: 9.9844301 | F24: =E24*C24 -> 89.859871 | G24: =E24*5.1737 -> 51.656446
A25: P1560 | B25: 6114.30.00 | C25: 26 | D25: =VLOOKUP(A25,PULSE!A:C,3,0) -> 22.78 | E25: 12.427872 | F25: =E25*C25 -> 323.12468 | G25: =E25*5.1737 -> 64.298083
A26: P1581 | B26: 6104.63.00 | C26: 12 | D26: =VLOOKUP(A26,PULSE!A:C,3,0) -> 21.98 | E26: 11.493431 | F26: =E26*C26 -> 137.92117 | G26: =E26*5.1737 -> 59.463565
... A29: P1591 | B29: 6104.63.00 | C29: 7 | D29: =VLOOKUP(A29,PULSE!A:C,3,0) -> 29.98 | E29: 10.493545 | F29: =E29*C29 -> 73.454818 | G29: =E29*5.1737 -> 54.290456
A30: P1593 | B30: 6109.90.00 | C30: 8 | D30: =VLOOKUP(A30,TIMELESS!A:C,3,FALSE) -> 19.98 | E30: 10.597997 | F30: =E30*C30 -> 84.783975 | G30: =E30*5.1737 -> 54.830856
A31: P1596 | B31: 6104.63.00 | C31: 20 | D31: =VLOOKUP(A31,PULSE!A:C,3,FALSE) -> 29.98 | E31: 8.993111 | F31: =E31*C31 -> 179.86222 | G31: =E31*5.1737 -> 46.527658
A32: P1601 | B32: 6102.20.00 | C32: 9 | D32: =VLOOKUP(A32,PULSE!A:C,3,0) -> 45.58 | E32: 10.754326 | F32: =E32*C32 -> 96.788935 | G32: =E32*5.1737 -> 55.639657
A33: P1602 | B33: 6104.62.00 | C33: 7 | D33: =VLOOKUP(A33,PULSE!A:C,3,0) -> 27.38 | E33: 10.570831 | F33: =E33*C33 -> 73.995814 | G33: =E33*5.1737 -> 54.690306
A34: P1603 | B34: 6104.62.00 | C34: 9 | D34: =VLOOKUP(A34,PULSE!A:C,3,0) -> 45.58 | E34: 9.961564 | F34: =E34*C34 -> 89.654076 | G34: =E34*5.1737 -> 51.538144
A35: P1628 | B35: 6102.30.00 | C35: 7 | D35: =VLOOKUP(A35,PULSE!A:C,3,0) -> 34.58 | E35: 10.504166 | F35: =E35*C35 -> 73.529161 | G35: =E35*5.1737 -> 54.345403
A36: P1629 | B36: 6114.30.00 | C36: 9 | D36: =VLOOKUP(A36,PULSE!A:C,3,0) -> 29.18 | E36: 10.702448 | F36: =E36*C36 -> 96.322034 | G36: =E36*5.1737 -> 55.371256
A37: P1666 | B37: 6114.30.00 | C37: 13 | D37: =VLOOKUP(A37,PULSE!A:C,3,0) -> 19.98 | E37: 10.920884 | F37: =E37*C37 -> 141.97149 | G37: =E37*5.1737 -> 56.501378
A38: P1927 | B38: 6106.20.00 | C38: 17 | D38: =VLOOKUP(A38,PULSE!A:C,3,0) -> 19.98 | E38: 11.437603 | F38: =E38*C38 -> 194.43925 | G38: =E38*5.1737 -> 59.174727
A39: P6200 | B39: 6114.30.00 | C39: 20 | D39: =VLOOKUP(A39,PULSE!A:C,3,0) -> 17.38 | E39: 12.150155 | F39: =E39*C39 -> 243.00311 | G39: =E39*5.1737 -> 62.861258

Sheet TIMELESS
A1: Referência | B1: Descrição | C1: Dólar
A2: 46557 | B2: UNISEX LIVE LONG SOCK | C2: 8.18
A3: 46562 | B3: REFLEX RACE PRO TOP | C3: 31.98
A4: 46563 | B4: REFLEX RACE PRO SHORTS | C4: 29.98
A5: 46564 | B5: RACE PRO REFLEX LEGGINGS | C5: 36.38
A6: 46565 | B6: AERO AIR MOVE TANK TOP | C6: 18.18
A7: 46566 | B7: AERO AIR MOVE T-SHIRT | C7: 19.98
A8: 46567 | B8: FRESH PRO GRAPHENE TOP | C8: 31.98
A9: 46568 | B9: FRESH PRO GRAPHENE SHORTS | C9: 33.78
A10: 46569 | B10: FRESH PRO GRAPHENE LEGGINGS | C10: 45.58
A11: 46570 | B11: FRESH PRO GRAPHENE TANK TOP | C11: 27.38
A12: 46573 | B12: ACE HYDEFIT ADAPTIV TOP | C12: 29.18
A13: 46574 | B13: ACE HYDEFIT ADAPTIV SKIRT | C13: 34.58
... A160: 46971 | B160: TRAIN EQUILIBRIUM COMFY TANK TOP | C160: 23.78
A161: F2791 | B161: MEN'S BIKE SLIM SHIRT | C161: 45.58
A162: F2792 | B162: BIKE 9 MEN SHORTS | C162: 31.98
A163: F2793 | B163: BM TRIATHLON MEN JUMPSUIT | C163: 59.18
A164: F2794 | B164: HARMONY BIKE SHIRT | C164: 45.58
A165: F2795 | B165: RACE PRO BIKE SHORTS | C165: 31.98
A166: F2796 | B166: BM TRIATHLON JUMPSUIT | C166: 59.18
A167: F2808 | B167: BIB SHORTS MEN | C167: 40.98
A168: F2809 | B168: BIB SHORTS RACE PRO BIKE | C168: 40.98
A169: I2129 | B169: MODAL SOFT SHORTS | C169: 40.98
A170: I2130 | B170: FUSION SKIN LEGGINGS | C170: 63.78
A171: I2131 | B171: FUSION SKIN RACERBACK TOP | C171: 54.58
A172: I2132 | B172: AERIS FORM JACKET | C172: 63.78
... A443: P8111 | B443: TRAIN COMFY MEN T-SHIRT | C443: 17.38
A444: 45716 | B444: LUMINA KNIT SHORTS SET | C444: 54.58
A445: 45719 | B445: LUMINA KNIT JUMPSUIT | C445: 49.98
A446: 45720 | B446: MIDI DRESS LUMINA KNIT | C446: 77.38
A447: 45724 | B447: ACQUA TOP AND THONG SET | C447: 45.98
A448: 45725 | B448: ORBIT ACQUA BATHING SUIT | C448: 45.98
A449: 45726 | B449: ML LINEUP ACQUA BATHING SUIT | C449: 49.98
A450: 45727 | B450: ML ZIP ACQUA CROPPED BLOUSE | C450: 31.98
A451: 45728 | B451: ML ACQUA BLOUSE | C451: 27.38
A452: 45729 | B452: ALLURE ADAPTIV TRIANGLE TOP | C452: 20.98
A453: 45730 | B453: ALLURE ADAPTIV TIE THONG | C453: 20.98
A454: 45731 | B454: ALLURE ADAPTIV TRIANGLE TOP | C454: 21.78
A455: 45732 | B455: ALLURE ADAPTIV HANG GLIDING THONG | C455: 14.18
... A499: 45790 | B499: SENSE KIDS SWIMSUIT | C499: 20.98
A500: BC182 | B500: SENSE HANG GLIDING THONG | C500: 13.38
A501: BC183 | B501: HOT PANTS SENSE THONG | C501: 16.78
A502: BC184 | B502: SENSE SWIMSUIT | C502: 29.18
A503: BC196 | B503: SLIM SENSE SWIMSUIT | C503: 27.58
A504: BC197 | B504: CUT SENSE TRACK TOP | C504: 20.98
A505: BC199 | B505: DRAPED SENSE STRAIGHT TOP | C505: 23.38
A506: BC200 | B506: THONG HOT PANTS HANG GLIDING | C506: 16.78
A507: BC201 | B507: MEN'S ACQUA SWIM TRUNKS | C507: 16.78
A508: BC203 | B508: ACQUA SWIMSUIT | C508: 27.58
A509: BC499 | B509: SWIN MEN SENSE SWIM TRUNKS | C509: 16.78
A510: BC704 | B510: SENSE TRIANGLE TOP | C510: 14.98
A511: BC708 | B511: UP SENSE TIE-UP THONG | C511: 18.38
... A516: IB004 | B516: SWIM 8 MEN SHORTS | C516: 40.98

Sheet PULSE
A1: Referência | B1: Descrição | C1: Dólar
A2: 61855 | B2: Top Stride Softness | C2: 22.78
A3: 61856 | B3: Shorts Stride Softness | C3: 22.78
A4: 61857 | B4: Stride Softness Pants | C4: 27.38
A5: 61862 | B5: Legging Curve Sparkflow | C5: 22.78
A6: 61865 | B6: Top Trace Upfit | C6: 25.58
A7: 61867 | B7: Upfit Leggings | C7: 27.38
A8: 61870 | B8: Split Jog Jacket | C8: 36.38
A9: 61871 | B9: Barrel Jog Pants | C9: 40.98
A10: 61872 | B10: Long Balloon Jog Jumpsuit | C10: 54.58
A11: 61877 | B11: Cropped Long Nylon Net Jacket | C11: 54.58
A12: 85330 | B12: Top Halter ByNature | C12: 25.58
A13: 85331 | B13: Shorts ByNature | C13: 29.98
... A267: 61971 | B267: Run Move 9 Men's Shorts | C267: 36.38
A268: F2364 | B268: LIVE BT Bag | C268: 16.38
A269: F2418 | B269: Seamless Shorts Jumpsuit | C269: 29.98
A270: F2764 | B270: Seamless Knit Jumpsuit | C270: 32.78
A271: F2764 | B271: Seamless Knit Jumpsuit | C271: 32.78
A272: F2791 | B272: Bike Slim Men Shirt | C272: 45.58
A273: F2792 | B273: Shorts Bike 9 Men | C273: 31.98
A274: F2793 | B274: BM Triathlon Men Jumpsuit | C274: 59.18
A275: F2794 | B275: Harmony Bike Shirt | C275: 45.58
A276: F2795 | B276: Race Pro Bike Shorts | C276: 31.98
A277: F2796 | B277: BM Triathlon Jumpsuit | C277: 59.18
A278: F2808 | B278: Bretelle Bike Men | C278: 40.98
A279: F2809 | B279: Bretelle Race Pro Bike | C279: 40.98
... A623: P1686 | B623: Energy Dry Towel | C623: 7.38
A624: P1696 | B624: 0 | C624: 36.38
A625: P1697 | B625: 0 | C625: 40.98
A626: P1698 | B626: 0 | C626: 27.38
A627: P1719 | B627: Thermo Color Glove | C627: 15.58
A628: P1927 | B628: Cropped Tank Top Move Sense | C628: 19.98
A629: P4405 | B629: Fast Running Sock | C629: 5.58
A630: P6200 | B630: Top Slim BT Sense | C630: 17.38
A631: P8111 | B631: Train Comfy Men T-Shirt | C631: 16.38
A632: P8111 | B632: Train Comfy Men T-Shirt | C632: 16.38

Sheet ORIGINS
A1: Referência | B1: Descrição | D1: Dólar
A2: 46277 | B2: GRADIENT SEAMLESS KNIT® TOP | C2: 113.9 | D2: 22.78
A3: 46278 | B3: GRADIENT SEAMLESS KNIT® LEGGINGS | C3: 99.9 | D3: 19.98
A4: 46279 | B4: SEAMLESS KNIT® EDGE TOP | C4: 118.9 | D4: 23.78
A5: 46280 | B5: SEAMLESS KNIT® EDGE LEGGING | C5: 113.9 | D5: 22.78
A6: 46283 | B6: TOP V SWIMMER NEOPRENE FIT | C6: 113.9 | D6: 22.78
A7: 46284 | B7: BERMUDA NEOPRENE FIT | C7: 113.9 | D7: 22.78
A8: 46285 | B8: FIT NEOPRENE LEGGINGS | C8: 127.9 | D8: 25.58
A9: 46286 | B9: HALTER AIR MOVE TANK TOP® | C9: 77.9 | D9: 15.58
A10: 46287 | B10: AIR MOVE® BLOUSE | C10: 77.9 | D10: 15.58
A11: 46288 | B11: AIR MOVE® T-SHIRT | C11: 90.9 | D11: 18.18
A12: 46289 | B12: TOP HYDEFIT® ADAPTIV ACT | C12: 99.9 | D12: 19.98
A13: 46290 | B13: HYDEFIT® ADAPTIV ACT SHORTS | C13: 90.9 | D13: 18.18
... A187: 46551 | B187: LEGGING LIVE! HYDEFIT® ADAPTIV | C187: 145.9 | D187: 29.18
A188: F2364 | B188: LIVE BT BAG | C188: 81.9 | D188: 17.24
A189: F2777 | B189: SEAMLESS KNIT® DIAGONAL SHORTS | C189: 90.9 | D189: 18.926316
A190: F2778 | B190: SEAMLESS DIAGONAL FUSO PANTS | C190: 127.9 | D190: 26.926316
A191: F2780 | B191: SEAMLESS DIAGONAL JUMPSUIT | C191: 181.9 | D191: 38.294737
A192: F2782 | B192: SEAMLESS DIAGONAL JACKET | C192: 272.9 | D192: 57.452632
A193: F2797 | B193: BIKE VELOCI STRIPES T-SHIRT | C193: 195.9 | D193: 41.242105
A194: F2798 | B194: TRIATHLON BERMUDA JUMPSUIT | C194: 295.9 | D194: 62.294737
A195: F2799 | B195: RACE PRO® HARMONY BIKE SHORTS | C195: 181.9 | D195: 38.294737
A196: F2800 | B196: RACE PRO® HARMONY BIKE SHORTS | C196: 159.9 | D196: 33.663158
A197: F2802 | B197: BIKE VELOCI MEN T-SHIRT | C197: 195.9 | D197: 41.242105
A198: F2803 | B198: MEN'S TRIATHLON SHORTS JUMPSUIT | C198: 295.9 | D198: 62.294737
A199: F2804 | B199: RACE PRO MEN BIKE SHORTS | C199: 159.9 | D199: 33.663158
... A465: P8111 | B465: BASIC COMFORT MEN T-SHIRT | C465: 81.9 | D465: 15.35
A466: 45575 | B466: TOP CORTININHA SWAY | C466: 95.9 | D466: 19.18
A467: 45576 | B467: TOP SWAY TRACK | C467: 108.9 | D467: 21.78
A468: 45577 | B468: TOP V SWAY | C468: 108.9 | D468: 21.78
A469: 45578 | B469: SWAY TIE THONG | C469: 95.9 | D469: 19.18
A470: 45579 | B470: SWAY SIDE TIE THONG | C470: 91.9 | D470: 18.38
A471: 45580 | B471: SWAY THONG | C471: 70.9 | D471: 14.18
A472: 45581 | B472: V SWAY SWIMSUIT | C472: 145.9 | D472: 29.18
A473: 45582 | B473: MAXI SAND DUNES TRIANGLE TOP | C473: 99.9 | D473: 19.98
A474: 45583 | B474: TWIST SAND DUNES STRIPE TOP | C474: 108.9 | D474: 21.78
A475: 45584 | B475: TOP LOOP SAND DUNES | C475: 116.9 | D475: 23.38
A476: 45585 | B476: SAND DUNES TIE-UP THONG | C476: 95.9 | D476: 19.18
A477: 45586 | B477: SAND DUNES HANG GLIDING THONG | C477: 66.9 | D477: 13.38
... A592: 45711 | B592: SPELL MIDI DRESS | C592: 204.9 | D592: 40.98
A593: BC042 | B593: SWIN SEA DUSK KIDS SWIM TRUNKS | C593: 58.9 | D593: 11.78
A594: BC068 | B594: SENSE WIRE TIE THONG® | C594: 66.9 | D594: 13.38
A595: BC070 | B595: SENSE® LACING THONG | C595: 91.9 | D595: 18.38
A596: BC096 | B596: BERMUDA DRYSIDE DUSK KIDS | C596: 90.9 | D596: 18.18
A597: BC180 | B597: TOP V SENSE® | C597: 116.9 | D597: 23.38
A598: BC181 | B598: MAXI SENSE® THONG | C598: 70.9 | D598: 14.18
A599: BC182 | B599: SENSE® HANG GLIDING THONG | C599: 66.9 | D599: 13.38
A600: BC183 | B600: HOT PANT SENSE® THONG | C600: 83.9 | D600: 16.78
A601: BC184 | B601: SENSE SWIMSUIT® | C601: 137.9 | D601: 27.58
A602: BC185 | B602: TOP KNOT SENSE® | C602: 91.9 | D602: 18.38
A603: BC186 | B603: SENSE THONG® | C603: 83.9 | D603: 16.78
A604: BC196 | B604: SLIM SENSE® SWIMSUIT | C604: 124.9 | D604: 24.98
... A614: IB001 | B614: BEACH CAP | C614: 145.9 | D614: 29.18
A615: P1570 | B615: Top Curve Allure Adaptiv | D615: 18.93
A616: P1570 | B616: Top Curve Allure Adaptiv | D616: 18.93
A617: P1570 | B617: Top Curve Allure Adaptiv | D617: 18.93
A618: P0103 | B618: Top Neo Allure Adaptiv | D618: 23.98
A619: P0103 | B619: Top Neo Allure Adaptiv | D619: 23.98
A620: P0103 | B620: Top Neo Allure Adaptiv | D620: 23.98
A621: P0146 | B621: Shorts Fit Allure Adaptiv | D621: 23.14
A622: P0146 | B622: Shorts Fit Allure Adaptiv | D622: 23.14
A623: P1292 | B623: Shorts Fit Allure Adaptiv | D623: 23.14
A624: P1147 | B624: Bermuda Allure Adaptiv | D624: 23.98
A625: P1147 | B625: Bermuda Allure Adaptiv | D625: 23.98
A626: P1161 | B626: Bermuda Allure Adaptiv | D626: 26.93
... A744: F2787 | B744: Legging Legging Seamless | D744: 21.03
A745: 52473 | B745: Top Nadador Athletic Pro | D745: 21.03
A746: 52474 | B746: Legging Legging Athletic Pro | D746: 26.93
A747: 52475 | B747: Conjunto Shorts e Pochete | D747: 38.29
A748: 52476 | B748: Jaqueta Sem Capuz Dryside Ting. Interno | D748: 47.98
A749: 52477 | B749: Top Nadador Allure® Mat Adaptiv | D749: 25.03
A750: 52478 | B750: Shorts Basico Allure® Mat Adaptiv | D750: 23.98
A751: 52479 | B751: Legging Legging Allure® Mat Adaptiv | D751: 28.82
A752: 52480 | B752: Regata Nadador Athletic Pro | D752: 15.35
A753: 52481 | B753: Blusa Manga Curta Bio Stretch | D753: 21.03
A754: 52481 | B754: Blusa Manga Curta Bio Stretch | D754: 21.03
A755: 52482 | B755: Regata Basica Bio Stretch | D755: 21.03
A756: 52482 | B756: Regata Basica Bio Stretch | D756: 21.03
... A794: 52504 | B794: Blusa Manga Curta Breezy Skin | D794: 18.29
A795: P1310 | B795: Top Speed Power | D795: 28.82
A796: P1295 | B796: Bermuda 6 Pockets Run Speed | D796: 31.56
A797: P1309 | B797: Legging 6 Pockets Speed | D797: 40.19
A798: P1332 | B798: Regata Harmony | D798: 17.24
A799: P1330 | B799: Blusa Harmony | D799: 21.03
A800: P1311 | B800: Camiseta Cropped Ml Harmony | D800: 21.03
A801: P1331 | B801: Jaqueta Harmony | D801: 34.51
A802: 52505 | B802: Top Alca Race Pro® | D802: 33.66
A803: 52506 | B803: Bermuda Bermuda Race Pro® | D803: 26.93
A804: 52507 | B804: Legging Legging Race Pro® | D804: 33.66
A805: 52508 | B805: Blusa Cropped Broad | D805: 25.03
A806: 52509 | B806: Blusa Manga Curta Broad | D806: 18.29
A807: 52510 | B807: Regata Nadador Broad | D807: 18.29
A808: 52511 | B808: Top Nadador Athletic Pro | D808: 26.93
A809: 52512 | B809: Legging Legging Athletic Pro | D809: 28.82
A810: 52513 | B810: Jaqueta Com Capuz Dryside | D810: 57.45
A811: 52514 | B811: Shorts Com Short Dryside | D811: 33.66
A812: F2783 | B812: Top Alca Seamless | D812: 23.14
A813: F2777 | B813: Shorts Seamless Diagonal | D813: 18.93
A814: F2778 | B814: Calca Fuso Seamless Diagonal | D814: 26.93
A815: F2780 | B815: Macaquinho Seamless Diagonal | D815: 38.29
...

Sheet JOURNEY
A1: Referência | B1: Descrição | C1: Description | D1: Sell In | E1: Sell Out | F1: Dólar
A2: P1227 | B2: Top Curve Seamless | C2: SEAMLESS CURVE TOP | D2: 43.9 | E2: 94.9 | F2: =D2/4.75 -> 9.2421053
A3: P1228 | B3: Calcinha Basica Seamless | C3: BASIC SEAMLESS PANTY | D3: 31.9 | E3: 69.9 | F3: =D3/4.75 -> 6.7157895
A4: P1229 | B4: Calcinha String Push Seamless | C4: STRING PUSH SEAMLESS PANT | D4: 34.9 | E4: 74.9 | F4: =D4/4.75 -> 7.3473684
A5: P1383 | B5: Kit Calcinha Fio | C5: THONG PANTY KIT | D5: 59.9 | E5: 129.9 | F5: =D5/4.75 -> 12.610526
A6: P1188 | B6: Top Faixa Seamless | C6: SEAMLESS BANDEAU TOP | D6: 17.9 | E6: 39.9 | F6: =D6/4.75 -> 3.7684211
A7: P1189 | B7: Top Reto Seamless | C7: SEAMLESS STRAIGHT TOP | D7: 36.9 | E7: 79.9 | F7: =D7/4.75 -> 7.7684211
A8: P1191 | B8: Calcinha Fio Basica Seamless | C8: BASIC SEAMLESS THONG | D8: 27.9 | E8: 59.9 | F8: =D8/4.75 -> 5.8736842
A9: P1194 | B9: Calcinha Fio Media Seamless | C9: MEDIUM COVERAGE SEAMLESS THONG | D9: 34.9 | E9: 74.9 | F9: =D9/4.75 -> 7.3473684
A10: P1196 | B10: Cueca Longa Boxer Seamless | C10: LONG BOXER SEAMLESS UNDERWEAR | D10: 40.9 | E10: 89.9 | F10: =D10/4.75 -> 8.6105263
A11: P1195 | B11: Cueca Boxer Seamless | C11: SEAMLESS BOXER BRIEF | D11: 36.9 | E11: 79.9 | F11: =D11/4.75 -> 7.7684211
A12: P1407 | B12: Cinto Seamless | C12: SEAMLESS BELT | D12: 45.9 | E12: 99.9 | F12: =D12/4.75 -> 9.6631579
A13: P1290 | B13: Porta Objetos Live! Movement | C13: LIVE! MOVEMENT ORGANIZER | D13: 45.9 | E13: 99.9 | F13: =D13/4.75 -> 9.6631579
... A128: P1133 | B128: Macacao Allure Adaptiv | C128: ALLURE ADAPTIV JUMPSUIT | D128: 195.9 | E128: 429.9 | F128: =D128/4.75 -> 41.242105
A129: 85091 | B129: Top Allure Matt | C129: ALLURE MATT TOP | D129: 118.9 | E129: 259.9 | F129: =D129/4.75 -> 25.031579
A130: 85092 | B130: Bermuda Allure Matt | C130: ALLURE MATT SHORTS | D130: 113.9 | E130: 249.9 | F130: =D130/4.75 -> 23.978947
A131: 85093 | B131: Calca Allure Matt | C131: ALLURE MATT PANTS | D131: 127.9 | E131: 279.9 | F131: =D131/4.75 -> 26.926316
A132: 85094 | B132: Regata Bio Stretch | C132: BIO STRETCH TANK TOP | D132: 122.9 | E132: 269.9 | F132: =D132/4.75 -> 25.873684
A133: 85095 | B133: Camiseta Bio Stretch | C133: BIO STRETCH T-SHIRT | D133: 158.9 | E133: 349.9 | F133: =D133/4.75 -> 33.452632
A134: 85096 | B134: Top Athletic Pro | C134: ATHLETIC PRO TOP | D134: 127.9 | E134: 279.9 | F134: =D134/4.75 -> 26.926316
A135: 85097 | B135: Legging Athletic Pro | C135: ATHLETIC PRO LEGGING | D135: 104.9 | E135: 229.9 | F135: =D135/4.75 -> 22.084211
A136: 85098 | B136: Jaqueta Dryside | C136: DRYSIDE JACKET | D136: 227.9 | E136: 499.9 | F136: =D136/4.75 -> 47.978947
A137: 85099 | B137: Shorts Dryside | C137: DRYSIDE SHORTS | D137: 158.9 | E137: 349.9 | F137: =D137/4.75 -> 33.452632
A138: 85058 | B138: Blusão Soft Pure | C138: SOFT PURE JACKET | D138: 158.9 | E138: 349.9 | F138: =D138/4.75 -> 33.452632
A139: 85059 | B139: Calca Soft Pure | C139: SOFT PURE PANTS | D139: 190.9 | E139: 419.9 | F139: =D139/4.75 -> 40.189474
A140: 85057 | B140: Vestido Soft Pure | C140: SOFT PURE DRESS | D140: 272.9 | E140: 599.9 | F140: =D140/4.75 -> 57.452632
A141: F2776 | B141: Top Seamless | C141: SEAMLESS TOP | D141: 127.9 | E141: 279.9 | F141: =D141/4.75 -> 26.926316
A142: IP054 | B142: Saia Importado | C142: AERO VISION SKIRT | D142: 158.9 | E142: 349.9 | F142: =D142/4.75 -> 33.452632
A143: IP053 | B143: Jaqueta Nylon Racer | C143: NYLON RACER JACKET | D143: 249.9 | E143: 549.9 | F143: =D143/4.75 -> 52.610526
A144: I4117 | B144: Jaqueta Importado | C144: AERO VISION JACKET | D144: 272.9 | E144: 599.9 | F144: =D144/4.75 -> 57.452632
A145: I4111 | B145: Shorts Importado | C145: SHORTS | D145: 158.9 | E145: 349.9 | F145: =D145/4.75 -> 33.452632
A146: F2777 | B146: Shorts Seamless | C146: SEAMLESS SHORTS | D146: 89.9 | E146: 199.9 | F146: =D146/4.75 -> 18.926316
A147: F2780 | B147: Macaquinho Seamless | C147: SEAMLESS JUMPSUIT | D147: 181.9 | E147: 399.9 | F147: =D147/4.75 -> 38.294737
A148: F2778 | B148: Fusô Seamless | C148: SEAMLESS LEGGING | D148: 127.9 | E148: 279.9 | F148: =D148/4.75 -> 26.926316
A149: 85109 | B149: Top Hydefit | C149: HYDEFIT TOP | D149: 136.9 | E149: 299.9 | F149: =D149/4.75 -> 28.821053
A150: 85110 | B150: Shorts Hydefit | C150: HYDEFIT SHORTS | D150: 89.9 | E150: 199.9 | F150: =D150/4.75 -> 18.926316
A151: 85125 | B151: Legging Hydefit | C151: HYDEFIT LEGGING | D151: 127.9 | E151: 279.9 | F151: =D151/4.75 -> 26.926316
A152: 85106 | B152: Regata New Ribbed Knit | C152: NEW RIBBED KNIT TANK TOP | D152: 68.9 | E152: 149.9 | F152: =D152/4.75 -> 14.505263
A153: 85105 | B153: Camiseta New Ribbed Knit | C153: NEW RIBBED KNIT T-SHIRT | D153: 72.9 | E153: 159.9 | F153: =D153/4.75 -> 15.347368
A154: 85104 | B154: Camiseta New Ribbed Knit | C154: NEW RIBBED KNIT T-SHIRT | D154: 77.9 | E154: 169.9 | F154: =D154/4.75 -> 16.4
A155: 85100 | B155: Top Seamless | C155: SEAMLESS TOP | D155: 113.9 | E155: 249.9 | F155: =D155/4.75 -> 23.978947
A156: 85101 | B156: Legging Seamless | C156: SEAMLESS LEGGING | D156: 104.9 | E156: 229.9 | F156: =D156/4.75 -> 22.084211
A157: 85108 | B157: Regata Broad | C157: BROAD TANK TOP | D157: 89.9 | E157: 199.9 | F157: =D157/4.75 -> 18.926316
A158: I4063 | B158: Jaqueta Ripstop Asics | C158: ASICS RIPSTOP JACKET | D158: 272.9 | E158: 599.9 | F158: =D158/4.75 -> 57.452632
A159: I4064 | B159: Shorts Ripstop Asics | C159: ASICS RIPSTOP SHORTS | D159: 158.9 | E159: 349.9 | F159: =D159/4.75 -> 33.452632
A160: I4065 | B160: Saia Ripstop Asics | C160: ASICS RIPSTOP SKIRT | D160: 154.9 | E160: 339.9 | F160: =D160/4.75 -> 32.610526
A161: P1431 | B161: Bermuda Speed Open | C161: SPEED OPEN SHORTS | D161: 149.9 | E161: 329.9 | F161: =D161/4.75 -> 31.557895
A162: P1432 | B162: Legging Speed Open | C162: SPEED OPEN LEGGING | D162: 149.9 | E162: 329.9 | F162: =D162/4.75 -> 31.557895
A163: 85113 | B163: Camiseta Broad | C163: BROAD T-SHIRT | D163: 89.9 | E163: 199.9 | F163: =D163/4.75 -> 18.926316
A164: 85114 | B164: Top Active | C164: ACTIVE TOP | D164: 127.9 | E164: 279.9 | F164: =D164/4.75 -> 26.926316
A165: 85115 | B165: Shorts Active | C165: ACTIVE SHORTS | D165: 109.9 | E165: 239.9 | F165: =D165/4.75 -> 23.136842
A166: 85116 | B166: Calca Active | C166: ACTIVE PANTS | D166: 149.9 | E166: 329.9 | F166: =D166/4.75 -> 31.557895
A167: 85119 | B167: Top Allure | C167: ALLURE TOP | D167: 113.9 | E167: 249.9 | F167: =D167/4.75 -> 23.978947
A168: 85120 | B168: Bermuda Allure | C168: ALLURE SHORTS | D168: 89.9 | E168: 199.9 | F168: =D168/4.75 -> 18.926316
A169: 85121 | B169: Legging Allure | C169: ALLURE LEGGING | D169: 127.9 | E169: 279.9 | F169: =D169/4.75 -> 26.926316
A170: 85067 | B170: Kimono Soft Line | C170: SOFT LINE KIMONO | D170: 227.9 | E170: 499.9 | F170: =D170/4.75 -> 47.978947
A171: 85063 | B171: Blusão Soft Line | C171: SOFT LINE BLOUSE | D171: 158.9 | E171: 349.9 | F171: =D171/4.75 -> 33.452632
A172: 85068 | B172: Calca Soft Line | C172: SOFT LINE PANTS | D172: 227.9 | E172: 499.9 | F172: =D172/4.75 -> 47.978947
A173: 85129 | B173: Top Neopren Shine | C173: NEOPREN SHINE TOP | D173: 109.9 | E173: 239.9 | F173: =D173/4.75 -> 23.136842
A174: 85130 | B174: Fusô Neopren Shine | C174: NEOPREN SHINE LEGGING | D174: 163.9 | E174: 359.9 | F174: =D174/4.75 -> 34.505263
... A192: 85079 | B192: Fusô Seamless | C192: SEAMLESS LEGGING | D192: 127.9 | E192: 279.9 | F192: =D192/4.75 -> 26.926316
A193: F2782 | B193: Jaqueta Seamless | C193: SEAMLESS JACKET | D193: 272.9 | E193: 599.9 | F193: =D193/4.75 -> 57.452632
A194: 85122 | B194: Top Neopren | C194: NEOPREN TOP | D194: 136.9 | E194: 299.9 | F194: =D194/4.75 -> 28.821053
A195: 85123 | B195: Legging Neopren | C195: NEOPREN LEGGING | D195: 181.9 | E195: 399.9 | F195: =D195/4.75 -> 38.294737
A196: 85124 | B196: Bermuda Neopren | C196: NEOPREN SHORTS | D196: 118.9 | E196: 259.9 | F196: =D196/4.75 -> 25.031579
A197: F2802 | B197: Camisa Aerolight | C197: AEROLIGHT T-SHIRT | D197: 195.9 | E197: 429.9 | F197: =D197/4.75 -> 41.242105
A198: F2804 | B198: Bermuda Race Pro | C198: RACE PRO SHORTS | D198: 159.9 | E198: 349.9 | F198: =D198/4.75 -> 33.663158
A199: F2803 | B199: Macacao Aerolight | C199: AEROLIGHT JUMPSUIT | D199: 295.9 | E199: 649.9 | F199: =D199/4.75 -> 62.294737
A200: F2797 | B200: Camisa Aerolight | C200: AEROLIGHT T-SHIRT | D200: 195.9 | E200: 429.9 | F200: =D200/4.75 -> 41.242105
A201: F2799 | B201: Shorts Race Pro | C201: RACE PRO SHORTS | D201: 181.9 | E201: 399.9 | F201: =D201/4.75 -> 38.294737
A202: F2800 | B202: Bermuda Race Pro | C202: RACE PRO SHORTS | D202: 159.9 | E202: 349.9 | F202: =D202/4.75 -> 33.663158
A203: F2798 | B203: Macacao Aerolight | C203: AEROLIGHT JUMPSUIT | D203: 295.9 | E203: 649.9 | F203: =D203/4.75 -> 62.294737
A204: IP048 | B204: Jaqueta Importado | C204: WINDBREACKER JACKET | D204: 181.9 | E204: 399.9 | F204: =D204/4.75 -> 38.294737
A205: IP049 | B205: Shorts Importado | C205: SHORTS | D205: 136.9 | E205: 299.9 | F205: =D205/4.75 -> 28.821053
A206: 85181 | B206: Top Neoprene Line | C206: NEOPREN LINE TOP | D206: 118.9 | E206: 259.9 | F206: =D206/4.75 -> 25.031579
A207: 85183 | B207: Bermuda Neoprene Line | C207: NEOPREN LINE SHORTS | D207: 113.9 | E207: 249.9 | F207: =D207/4.75 -> 23.978947
A208: 85182 | B208: Fusô Neoprene Line | C208: NEOPREN LINE LEGGING | D208: 136.9 | E208: 299.9 | F208: =D208/4.75 -> 28.821053
A209: 85081 | B209: Jaqueta Soft Feel | C209: SOFT FEEL JACKET | D209: 317.9 | E209: 699.9 | F209: =D209/4.75 -> 66.926316
A210: 85082 | B210: Blusão Soft Feel | C210: SOFT FEEL BLOUSE | D210: 181.77273 | E210: 399.9 | F210: =D210/4.75 -> 38.267943
A211: 85083 | B211: Calca Soft Feel | C211: SOFT FEEL PANTS | D211: 249.9 | E211: 549.9 | F211: =D211/4.75 -> 52.610526
A212: I4085 | B212: Jaqueta Body Fabric | C212: BODY FABRIC JACKET | D212: 317.9 | E212: 699.9 | F212: =D212/4.75 -> 66.926316
A213: I4087 | B213: Calca Body Fabric | C213: BODY FABRIC PANTS | D213: 249.9 | E213: 549.9 | F213: =D213/4.75 -> 52.610526
A214: P1390 | B214: Regata Long Visco Heart | C214: VISCO HEART LONG SLEEVE TANK TOP | D214: 68.9 | E214: 149.9 | F214: =D214/4.75 -> 14.505263
A215: P1391 | B215: Regata Visco Heart | C215: VISCO HEART TANK TOP | D215: 72.9 | E215: 159.9 | F215: =D215/4.75 -> 15.347368
A216: P1392 | B216: Blusa Cropped Ml Visco Heart | C216: ML VISCO HEART CROPPED BLOUSE | D216: 72.9 | E216: 159.9 | F216: =D216/4.75 -> 15.347368
A217: P1393 | B217: Camiseta Ml Visco Heart | C217: ML VISCO HEART T-SHIRT | D217: 89.9 | E217: 199.9 | F217: =D217/4.75 -> 18.926316
A218: 85166 | B218: Top Rib Neo | C218: NEO RIB TOP | D218: 109.9 | E218: 239.9 | F218: =D218/4.75 -> 23.136842
A219: 85168 | B219: Shorts Rib Neo | C219: NEO RIB SHORTS | D219: 118.9 | E219: 259.9 | F219: =D219/4.75 -> 25.031579
A220: 85167 | B220: Fusô Rib Neo | C220: NEO RIB LEGGING | D220: 181.9 | E220: 399.9 | F220: =D220/4.75 -> 38.294737
A221: 85170 | B221: Regata Soft Pima | C221: SOFT PIMA TANK TOP | D221: 109.9 | E221: 239.9 | F221: =D221/4.75 -> 23.136842
A222: 85169 | B222: Camiseta Soft Pima | C222: SOFT PIMA T-SHIRT | D222: 136.9 | E222: 299.9 | F222: =D222/4.75 -> 28.821053
A223: 85171 | B223: Camiseta Soft Pima | C223: SOFT PIMA T-SHIRT | D223: 113.9 | E223: 249.9 | F223: =D223/4.75 -> 23.978947
A224: 85172 | B224: Jaqueta Sense Pro Fleece | C224: SENSE PRO FLEECE JACKET | D224: 204.9 | E224: 449.9 | F224: =D224/4.75 -> 43.136842
A225: 85173 | B225: Calca Sense Pro Fleece | C225: SENSE PRO FLEECE PANTS | D225: 181.9 | E225: 399.9 | F225: =D225/4.75 -> 38.294737
A226: 85146 | B226: Top Race Pro | C226: RACE PRO TOP | D226: 163.9 | E226: 359.9 | F226: =D226/4.75 -> 34.505263
A227: 85148 | B227: Legging Race Pro | C227: RACE PRO LEGGING | D227: 145.9 | E227: 319.9 | F227: =D227/4.75 -> 30.715789
A228: 85147 | B228: Shorts Race Pro | C228: RACE PRO SHORTS | D228: 181.9 | E228: 399.9 | F228: =D228/4.75 -> 38.294737
A229: I4057 | B229: Jaqueta Importado | C229: SQUARE JACKET | D229: 249.9 | E229: 549.9 | F229: =D229/4.75 -> 52.610526
A230: I4058 | B230: Shorts Importado | C230: SQUARE SHORTS | D230: 172.9 | E230: 379.9 | F230: =D230/4.75 -> 36.4
A231: I4060 | B231: Jaqueta Importado | C231: JACKET | D231: 409.9 | E231: 899.9 | F231: =D231/4.75 -> 86.294737
...

Sheet ALIVE
A1: Referência | B1: Descrição | C1: Tradução | D1: Sell In | E1: Sell Out | F1: Dólar
A2: 46000 | B2: Cinto Seamless | C2: SEAMLESS BELT | D2: 45.9 | E2: 99.9 | F2: =D2/4.5 -> 10.2
A3: 46001 | B3: Blusa Raglan Seamless | C3: SEAMLESS RAGLAN BLOUSE | D3: 89.9 | E3: 199.9 | F3: =D3/4.5 -> 19.977778
A4: 46003 | B4: Camiseta Seamless | C4: SEAMLESS T-SHIRT | D4: 72.9 | E4: 159.9 | F4: =D4/4.5 -> 16.2
A5: 46004 | B5: Regata Seamless Men | C5: MEN SEAMLESS TANK TOP | D5: 68.9 | E5: 149.9 | F5: =D5/4.5 -> 15.311111
A6: 46005 | B6: Blusão | C6: BLOUSE | D6: 204.9 | E6: 449.9 | F6: =D6/4.5 -> 45.533333
A7: 46006 | B7: Calça | C7: PANTS | D7: 227.9 | E7: 499.9 | F7: =D7/4.5 -> 50.644444
A8: 46007 | B8: Bermuda Move | C8: MOVE SHORT | D8: 159.9 | E8: 349.9 | F8: =D8/4.5 -> 35.533333
A9: 46008 | B9: Camiseta | C9: T-SHIRT | D9: 80.9 | E9: 179.9 | F9: =D9/4.5 -> 17.977778
A10: 46009 | B10: Faixa de Cabelo Seamless | C10: SEAMLESS HAIR BAND | D10: 36.9 | E10: 79.9 | F10: =D10/4.5 -> 8.2
A11: 46010 | B11: Camiseta Comfy Flame LIVE! Men | C11: LIVE! MEN COMFY FLAME T-SHIRT | D11: 72.9 | E11: 159.9 | F11: =D11/4.5 -> 16.2
A12: 46011 | B12: Camiseta Comfy Connect Men | C12: MEN COMFY CONNECT T-SHIRT | D12: 72.9 | E12: 159.9 | F12: =D12/4.5 -> 16.2
A13: 46012 | B13: Camiseta Comfy Lines Men | C13: MEN COMFY LINES T-SHIRT | D13: 72.9 | E13: 159.9 | F13: =D13/4.5 -> 16.2
... A168: 46204 | B168: Blusa Ribbed Knit Kids | C168: KIDS RIBBER KNIT BLOUSE | D168: 54.9 | E168: 119.9 | F168: =D168/4.5 -> 12.2
A169: F2216 | B169: Meia Sapatilha Invisible | C169: INVISIBLE SOCK | D169: 26.9 | E169: 69.9 | F169: =D169/4.5 -> 5.9777778
A170: F2222 | B170: Kit Meias Workout | C170: KIT WORKOUT SOCKS | D170: 45.9 | E170: 109.9 | F170: =D170/4.5 -> 10.2
A171: F2758 | B171: Sunga Men Acqua | C171: MEN ACQUA TRUNK | D171: 81.9 | E171: 179.9 | F171: =D171/4.5 -> 18.2
A172: F2759 | B172: Bermuda Men Acqua | C172: MEN ACQUA SHORT | D172: 89.9 | E172: 199.9 | F172: =D172/4.5 -> 19.977778
A173: F2760 | B173: Maiô Acqua | C173: ACQUA SWIMSUIT | D173: 127.9 | E173: 279.9 | F173: =D173/4.5 -> 28.422222
A174: F2762 | B174: Top Explore Seamless Knit® | C174: EXPLORE SEAMLESS KNIT TOP | D174: 89.9 | E174: 199.9 | F174: =D174/4.5 -> 19.977778
A175: F2763 | B175: Legging Explore Seamless Knit® | C175: EXPLORE SEAMLESS KNIT LEGGING | D175: 136.9 | E175: 299.9 | F175: =D175/4.5 -> 30.422222
A176: F2764 | B176: Macacão Shorts Seamless Knit® | C176: SEAMLESS KNIT SHORT JUMPSUIT | D176: 136.9 | E176: 299.9 | F176: =D176/4.5 -> 30.422222
A177: F2765 | B177: Top V Rib Classic Seamless | C177: RIBE CLASSIC SEAMLESS V TOP | D177: 89.9 | E177: 199.9 | F177: =D177/4.5 -> 19.977778
A178: F2769 | B178: Legging Rib Classic Seamless | C178: RIB CLASSIC SEAMLESS LEGGING | D178: 113.9 | E178: 249.9 | F178: =D178/4.5 -> 25.311111
A179: F2770 | B179: Shorts Rib Classic Seamless | C179: RIB CLASSIC SEAMLESS SHORT | D179: 81.9 | E179: 179.9 | F179: =D179/4.5 -> 18.2
A180: F2771 | B180: Regata | C180: TANK TOP | D180: 68.9 | E180: 149.9 | F180: =D180/4.5 -> 15.311111
... A321: P1254 | B321: Legging Icon Neo Kids | C321: KIDS ICON NEO LEGGING | D321: 77.9 | E321: 169.9 | F321: =D321/4.5 -> 17.311111
A322: P1265 | B322: Bolsa Live! Everyday | C322: LIVE! EVERYDAY BAG | D322: 33.9 | E322: BOLSA PARA VENDEDORAS LOJA | F322: =D322/4.5 -> 7.5333333
A323: P1267 | B323: Top Wide | C323: WIDE TOP | D323: 99.9 | E323: 219.9 | F323: =D323/4.5 -> 22.2
A324: P1268 | B324: Vestido Fit Hydefit® Adaptiv | C324: HYDEFIT ADAPTIV FIT DRESS | D324: 168.9 | E324: 369.9 | F324: =D324/4.5 -> 37.533333
A325: P1270 | B325: Calça Flare Allure® Adaptiv | C325: ALLURE ADAPTIV PANTS | D325: 145.9 | E325: 319.9 | F325: =D325/4.5 -> 32.422222
A326: P1272 | B326: Shorts Fit Icon Neo Reflex | C326: ICON NEO REFLEX FIT SHORT | D326: 99.9 | E326: 219.9 | F326: =D326/4.5 -> 22.2
A327: P1273 | B327: Calça Fusô Icon Neo Reflex | C327: ICON NEO REFLEX PANTS | D327: 135.9 | E327: 299.9 | F327: =D327/4.5 -> 30.2
A328: P1275 | B328: Camiseta Icon Reflex Comfort | C328: ICON REFLEX COMFORT T-SHIRT | D328: 81.9 | E328: 179.9 | F328: =D328/4.5 -> 18.2
A329: P1277 | B329: Regata Cropped LIVE! Reflex | C329: LIVE! REFLEX CROPPED TANK TOP | D329: 72.9 | E329: 159.9 | F329: =D329/4.5 -> 16.2
A330: P1279 | B330: Camiseta ML Thermo Skin | C330: THERMO SKIN T-SHIRT | D330: 99.9 | E330: 219.9 | F330: =D330/4.5 -> 22.2
A331: P1280 | B331: Legging Sense Pro Fleece | C331: SENSE PRO FLEECE LEGGING | D331: 99.9 | E331: 219.9 | F331: =D331/4.5 -> 22.2
A332: P1281 | B332: Regata Comfy Bio Stretch Men | C332: MEN COMFY BIO STRETCH TANK TOP | D332: 89.9 | E332: 199.9 | F332: =D332/4.5 -> 19.977778
A333: P1282 | B333: Shorts Run 3'' Dryside Men | C333: MEN RUN 3 DRYSIDE SHORT | D333: 113.9 | E333: 249.9 | F333: =D333/4.5 -> 25.311111
A334: P1285 | B334: Bermuda Pro 5'' Dryside | C334: PRO 5 DRYSIDE SHORT | D334: 127.9 | E334: 279.9 | F334: =D334/4.5 -> 28.422222
... A407: P1434 | B407: Top Curve Sense® | C407: SENSE CURVE TOP | D407: 81.9 | E407: 179.9 | F407: =D407/4.5 -> 18.2
A408: P1458 | B408: Bolsa Gold Essential | C408: GOLD ESSENTIAL BAG | D408: 125.9 | E408: BOLSA PARA LIVE! ATÉ VC | F408: =D408/4.5 -> 27.977778
A409: P1570 | B409: Top Curve Allure® Adaptiv | C409: ALLURE ADAPTIV CURVE TOP | D409: 86.9 | E409: 189.9 | F409: =D409/4.5 -> 19.311111
A410: P1719 | B410: Luva Termo Color | C410: TERMO COLOR GLOVE | D410: 68.9 | E410: 149.9 | F410: =D410/4.5 -> 15.311111
A411: P3006 | B411: Legging Active® | C411: ACTIVE LEGGING | D411: 113.9 | E411: 249.9 | F411: =D411/4.5 -> 25.311111
A412: P3054 | B412: Shorts Active | C412: ACTIVE SHORT | D412: 72.9 | E412: 159.9 | F412: =D412/4.5 -> 16.2
A413: P3412 | B413: Calça Fusô Active® | C413: ACTIVE PANTS | D413: 89.9 | E413: 199.9 | F413: =D413/4.5 -> 19.977778
A414: P4405 | B414: Meia Fast Running | C414: FAST RUNNING SOCKS | D414: 24.9 | E414: 59.9 | F414: =D414/4.5 -> 5.5333333
A415: P5134 | B415: Top Racer Sense® | C415: SENSE RACER TOP | D415: 81.9 | E415: 179.9 | F415: =D415/4.5 -> 18.2
A416: P5165 | B416: Camiseta Action | C416: ACTION T-SHIRT | D416: 68.9 | E416: 149.9 | F416: =D416/4.5 -> 15.311111
A417: P8111 | B417: Camiseta Basic Comfort Men | C417: MEN BASIC COMFORT T-SHIRT | D417: 72.9 | E417: 159.9 | F417: =D417/4.5 -> 16.2
A418: P8117 | B418: Legging LIVE! Sense® Pro | C418: LIVE! SENSE PRO LEGGING | D418: 127.9 | E418: 279.9 | F418: =D418/4.5 -> 28.422222
A419: 52342 | B419: TOP STATELY | C419: STATELY TOP | D419: 113.9 | E419: 249.9 | F419: 25.311111
A420: 52343 | B420: SHORTS STATELY | C420: STATELY SHORT | D420: 113.9 | E420: 249.9 | F420: 25.311111
A421: 52344 | B421: LEGGING STATELY | C421: STATELY LEGGING | D421: 127.9 | E421: 279.9 | F421: 28.422222
A422: 52345 | B422: TOP CROSS DUO COLLOR BYNATURE | C422: BYNATURE DUO COLLOR CROSS TOP | D422: 127.9 | E422: 279.9 | F422: 28.422222
A423: 52346 | B423: CALCA FUSO DUO COLLOR BYNATURE | C423: BYNATURE DUO COLLOR LEGGING | D423: 145.9 | E423: 319.9 | F423: 32.422222
A424: 52347 | B424: BERMUDA DUO COLLOR BYNATURE | C424: BYNATURE DUO COLLOR SHORT | D424: 113.9 | E424: 249.9 | F424: 25.311111
A425: 52349 | B425: BLUSA TRANSPASSADA WIDE | C425: WIDE BLOUSE | D425: 81.9 | E425: 179.9 | F425: 18.2
A426: 52350 | B426: CALÇA PANTACOURT TIE WIDE | C426: TIE WIDE PANTS | D426: 149.9 | E426: 329.9 | F426: 33.311111
A427: 52351 | B427: SHORTS TIE WIDE | C427: TIE WIDE SHORT | D427: 99.9 | E427: 219.9 | F427: 22.2
A428: 52352 | B428: TOP CROSS ATHLETIC PRO FUSION | C428: ATHLETIC PRO FUSION CROSS TOP | D428: 99.9 | E428: 219.9 | F428: 22.2
A429: 52353 | B429: LEGGING ATHLETIC PRO FUSION | C429: ATHLETIC PRO FUSION LEGGING | D429: 99.9 | E429: 219.9 | F429: 22.2
A430: 52354 | B430: SHORTS ATHLETIC PRO FUSION | C430: ATHLETIC PRO FUSION SHORT | D430: 81.9 | E430: 179.9 | F430: 18.2
... A479: 52408 | B479: BLUSA CROPPED FREE STEM | C479: FREE CROPPED BLOUSE | D479: 76.9 | E479: 169.9 | F479: 17.088889
A480: F2771 | B480: REGATA SEAMLESS KNIT | C480: SEAMLESS KNIT TANK TOP | D480: 68.9 | E480: 149.9 | F480: 15.311111
A481: F2772 | B481: BLUSA SEAMLESS KNIT | C481: SEAMLESS KNIT BLOUSE | D481: 86.9 | E481: 189.9 | F481: 19.311111
A482: F6001 | B482: BLUSA RAGLAN SEAMLESS | C482: RAGLAN SEAMLESS BLOUSE | D482: 89.9 | E482: 199.9 | F482: 19.977778
A483: F6003 | B483: CAMISETA COMFY RAGLAN SEAMLESS | C483: COMFY RAGLAN SEAMLESS T-SHIRT | D483: 72.9 | E483: 159.9 | F483: 16.2
A484: F6004 | B484: REGATA SEAMLESS MEN | C484: MEN SEAMLESS TANK TOP | D484: 68.9 | E484: 149.9 | F484: 15.311111
A485: F6133 | B485: REGATA SEAMLESS | C485: SEAMLESS TANK TOP | D485: 81.9 | E485: 179.9 | F485: 18.2
A486: P0022 | B486: TOP MOVE SENSE | C486: MOVE SENSE TOP | D486: 99.9 | E486: 219.9 | F486: 22.2
A487: P0060 | B487: SHORTS FIT LIVE SENSE PRO | C487: SENSE PRO FIT SHORT | D487: 89.9 | E487: 199.9 | F487: 19.977778
A488: P0063 | B488: TOP CURVE LIVE SENSE PRO | C488: SENSE PRO CURVE TOP | D488: 89.9 | E488: 199.9 | F488: 19.977778
A489: P0103 | B489: TOP NEO ALLURE ADAPTIV | C489: NEO ALLURE ADAPTIV TOP | D489: 109.9 | E489: 239.9 | F489: 24.422222
A490: P0141 | B490: CAMISETA ACTION SIDE | C490: ACTION SIDE T-SHIRT | D490: 89.9 | E490: 199.9 | F490: 19.977778
A491: P0146 | B491: SHORTS FIT ALLURE ADAPTIV | C491: ALLURE ADAPTIV FIT SHORT | D491: 89.9 | E491: 199.9 | F491: 19.977778
... A534: P8117 | B534: LEGGING LIVE SENSE PRO REFLEX | C534: LIVE SENSE PRO REFLEX LEGGING | D534: 127.9 | E534: 279.9 | F534: 28.422222
A535: 45440 | B535: Maiô ML Kids | C535: KIDS SWIMSUIT | D535: 124.9 | E535: 299.9 | F535: =D535/4.5 -> 27.755556
A536: 45441 | B536: Maiô Duo Cross Kids | C536: KIDS DUO CROSS SWIMSUIT | D536: 91.9 | E536: 219.9 | F536: =D536/4.5 -> 20.422222
A537: 45442 | B537: Biquini Cross Back Kids | C537: KIDS CROSS BACK TOP | D537: 95.9 | E537: 229.9 | F537: =D537/4.5 -> 21.311111
A538: 45443 | B538: Biquini Faixa Revesible Kids | C538: KIDS REVERSIBLE BAND TOP | D538: 104.9 | E538: 249.9 | F538: =D538/4.5 -> 23.311111
A539: 45444 | B539: Macacão Curto Wide Kids | C539: KIDS WIDE SHORT JUMPSUIT | D539: 89.9 | E539: 199.9 | F539: =D539/4.5 -> 19.977778
A540: 45445 | B540: Calça Reta Tricô | C540: STRAIGHT KNIT PANTS | D540: 249.9 | E540: 549.9 | F540: =D540/4.5 -> 55.533333
A541: 45446 | B541: Macacão Curto Primrose Kids | C541: KIDS PRIMROSE SHORT JUMPSUIT | D541: 99.9 | E541: 219.9 | F541: =D541/4.5 -> 22.2
A542: 45447 | B542: Kaftan V Wide Kids | C542: KIDS WIDE V KAFTAN | D542: 89.9 | E542: 199.9 | F542: =D542/4.5 -> 19.977778
A543: 45448 | B543: Regata Tricô | C543: KNITTING TANK TOP | D543: 159.9 | E543: 349.9 | F543: =D543/4.5 -> 35.533333
A544: 45449 | B544: Vestido Kids | C544: KIDS DRESS | D544: 99.9 | E544: 219.9 | F544: =D544/4.5 -> 22.2
A545: 45450 | B545: Cardigan Tricô | C545: KNITTING CARDIGAN | D545: 227.9 | E545: 499.9 | F545: =D545/4.5 -> 50.644444
A546: 45452 | B546: Vestido Tricô | C546: KNITTING DRESS | D546: 227.9 | E546: 499.9 | F546: =D546/4.5 -> 50.644444
... A649: 45573 | B649: Shorts Essential Wide Kids | C649: KIDS ESSENTIAL WIDE SHORT | D649: 68.9 | E649: 149.9 | F649: =D649/4.5 -> 15.311111
A650: BC042 | B650: Sunga Swin Kids | C650: IDS SWIM TRUNKS | D650: 58.9 | E650: 139.9 | F650: =D650/4.5 -> 13.088889
A651: BC068 | B651: Tanga Amarração Fio Sense® | C651: SENSE TIE BOTTOM | D651: 61.9 | E651: 149.9 | F651: =D651/4.5 -> 13.755556
A652: BC069 | B652: Maiô Top Faixa Nó Sense® | C652: SENSE KNOT BAND TOP SWIMSUIT | D652: 166.9 | E652: 399.9 | F652: =D652/4.5 -> 37.088889
A653: BC070 | B653: Tanga Amarração Sense® | C653: SENSE TIE BOTTOM | D653: 83.9 | E653: 199.9 | F653: =D653/4.5 -> 18.644444
A654: BC074 | B654: Chemise Viscose | C654: VISCOSE CHEMISE | D654: 178.9 | E654: 399.9 | F654: =D654/4.5 -> 39.755556
A655: BC079 | B655: Kimono Wide | C655: WIDE KIMONO | D655: 149.9 | E655: 329.9 | F655: =D655/4.5 -> 33.311111
A656: BC096 | B656: Bermuda Dryside Dusk Kids | C656: KIDS DRYSIDE DUSK SHORT | D656: 86.9 | E656: 189.9 | F656: =D656/4.5 -> 19.311111
A657: BC179 | B657: Top Faixa Cut Sense® | C657: SENSE CUT BAND TOP | D657: 98.9 | E657: 239.9 | F657: =D657/4.5 -> 21.977778
A658: BC180 | B658: Top V Sense® | C658: SENSE V TOP | D658: 116.9 | E658: 279.9 | F658: =D658/4.5 -> 25.977778
...

Sheet DREAMERS
A1: Referência | B1: Descrição | C1: Description | D1: Sell In | E1: Dolar
A2: 84758 | B2: TOP GROOVE LINE | C2: GROOVE LINE TOP | D2: 113.9 | E2: 25.311111
A3: 84759 | B3: SHORTS GROOVE LINE | C3: GROOVE LINE SHORT | D3: 89.9 | E3: 19.977778
A4: 84760 | B4: LEGGING GROOVE LINE | C4: GROOVE LINE LEGGING | D4: 145.9 | E4: 32.422222
A5: 84761 | B5: MACACAO GROOVE LINE | C5: GROOVE LINE JUMPSUIT | D5: 149.9 | E5: 33.311111
A6: 84762 | B6: CAMISETA CROPPED WIDE | C6: WIDE CROPPED T-SHIRT | D6: 68.9 | E6: 15.311111
A7: 84765 | B7: TOP DYNAMIC MAT | C7: DYNAMIC MAT TOP | D7: 113.9 | E7: 25.311111
A8: 84766 | B8: SHORTS DYNAMIC MAT | C8: DYNAMIC MAT SHORT | D8: 89.9 | E8: 19.977778
A9: 84767 | B9: LEGGING DYNAMIC MAT | C9: DYNAMIC MAT LEGGING | D9: 127.9 | E9: 28.422222
A10: 84770 | B10: REGATA WIDE | C10: WIDE TANK TOP | D10: 68.9 | E10: 15.311111
A11: 84772 | B11: CAMISETA COMFY MOVIMENT MEN | C11: MEN COMFY MOVIMENT T-SHIRT | D11: 72.9 | E11: 16.2
A12: 84773 | B12: CAMISETA COMFY STRIPE MEN | C12: MEN COMFY STRIPE T-SHIRT | D12: 72.9 | E12: 16.2
A13: 84774 | B13: CAMISETA COMFY HYPER MEN | C13: MEN COMFY HYPER T-SHIRT | D13: 72.9 | E13: 16.2
... A133: 84939 | B133: CALCA JOG EVERYDAY | C133: JOG EVERYDAY PANTS | D133: 172.9 | E133: 38.422222
A134: 84942 | B134: TOP SENSE FLEECE | C134: SENSE FLEECE TOP | D134: 109.9 | E134: 24.422222 | F134: =D134*0.4 -> 43.96
A135: 84943 | B135: FUSO SENSE FLEECE | C135: SENSE FLEECE LEGGING | D135: 127.9 | E135: 28.422222
A136: 84945 | B136: BERMUDA LIFT | C136: LIFT SHORT | D136: 113.9 | E136: 25.311111
A137: 84946 | B137: LEGGING LIFT | C137: LIFT LEGGING | D137: 127.9 | E137: 28.422222
A138: 84947 | B138: BLUSAO FROSTY | C138: FROSTY BLOUSE | D138: 159.9 | E138: 35.533333
A139: 84972 | B139: REGATA WIDE KIDS | C139: KIDS WIDE TANK TOP | D139: 54.9 | E139: 12.2
A140: 84973 | B140: CAMISETA WIDE KIDS | C140: KIDS WIDE T-SHIRT | D140: 59.9 | E140: 13.311111
A141: 84974 | B141: CAMISETA RIBBED KIDS | C141: KID RIBBED T-SHIRT | D141: 59.9 | E141: 13.311111
A142: 84975 | B142: LEGGING KIDS | C142: KIDS LEGGING | D142: 87.9 | E142: 19.533333
A143: 84976 | B143: LEGGING MAT KIDS | C143: KIDS MAT LEGGING | D143: 68.9 | E143: 15.311111
A144: 84977 | B144: JAQUETA FLEECE KIDS | C144: KIDS FLEECE JACKET | D144: 136.9 | E144: 30.422222
A145: 84978 | B145: CALCA FLEECE KIDS | C145: KIDS FLEECE PANTS | D145: 104.9 | E145: 23.311111
A146: 84979 | B146: JAQUETA JOG KIDS | C146: KIDS JOG JACKET | D146: 159.9 | E146: 35.533333
... A155: 84989 | B155: BERMUDA MOVE STREET MEN | C155: MEN MOVE STREET SHORT | D155: 136.9 | E155: 30.422222
A156: F2216 | B156: MEIA SAPATILHA INVISIBLE | C156: INVISIBLE ANKLE SOCKS | D156: 26.9 | E156: 5.9777778
A157: F2222 | B157: KIT MEIAS STRIDE | C157: STRIDE SOCKS KIT | D157: 45.9 | E157: 10.2
A158: F2369 | B158: REGATA FLOW | C158: FLOW TANK TOP | D158: 68.9 | E158: 15.311111
A159: F2435 | B159: CAMISETA ML FLOW | C159: FLOW T-SHIRT | D159: 89.9 | E159: 19.977778
A160: F2437 | B160: REGATA LONG FLOW | C160: LONG FLOW TANK TOP | D160: 63.9 | E160: 14.2
A161: F2662 | B161: TOP STRIPE SEAMLESS | C161: STRIPE SEAMLESS TOP | D161: 86.9 | E161: 19.311111
A162: F2666 | B162: FUSO STRIPE SEAMLESS | C162: STRIPE SEAMLESS LEGGING | D162: 89.9 | E162: 19.977778
A163: F2722 | B163: TOP CONTOUR SEAMLESS | C163: CONTOUR SEAMLESS TOP | D163: 89.9 | E163: 19.977778
A164: F2723 | B164: LEGGING CONTOUR SEAMLESS | C164: CONTOUR SEAMLESS LEGGING | D164: 89.9 | E164: 19.977778
A165: F2743 | B165: TOP DYNAMIC SEAMLESS | C165: DYNAMIC SEAMLESS TOP | D165: 89.9 | E165: 19.977778
A166: F2744 | B166: LEGGING DYNAMIC SEAMLESS | C166: DYNAMIC SEAMLESS LEGGING | D166: 113.9 | E166: 25.311111
A167: F2745 | B167: TOP STRIPE SEAMLESS | C167: STRIPE SEAMLESS TOP | D167: 81.9 | E167: 18.2
... A187: F4427 | B187: TOP AMAMENTACAO MATERNITY | C187: MATERNITY TOP | D187: 159.9 | E187: 35.533333
A188: F4428 | B188: LEGGING MATERNITY | C188: MATERNITY LEGGING | D188: 99.9 | E188: 22.2 | F188: =D188*0.4 -> 39.96
A189: F4647 | B189: CAMISETA CROPPED ML FLOW | C189: FLOW ML CROPPED T-SHIRT | D189: 68.9 | E189: 15.311111
A190: F4865 | B190: TOP GREEN | C190: GREEN TOP | D190: 113.9 | E190: 25.311111
A191: I4000 | B191: JAQUETA TEX PUFFER | C191: TEX PUFFER JACKET | D191: 318.9 | E191: 70.866667
A192: I4001 | B192: JAQUETA MAXI PUFFER REVERSIVEL | C192: REVERSIBLE MAXI PUFFER JACKET | D192: 409.9 | E192: 91.088889
A193: I4002 | B193: JAQUETA HYPE PUFFER | C193: HYPE PUFFER JACKET | D193: 317.9 | E193: 70.644444
A194: I4003 | B194: PARKA STREET | C194: STREET JACKET | D194: 318.9 | E194: 70.866667
A195: I4006 | B195: CALCA VELVETY | C195: VELVETY PANTS | D195: 194.9 | E195: 43.311111
A196: I4007 | B196: CALCA NYLON STREET | C196: NYLON STREET PANTS | D196: 181.9 | E196: 40.422222
A197: I4010 | B197: JAQUETA TECH PIXEL | C197: TECH PIXEL JACKET | D197: 272.9 | E197: 60.644444
A198: I4011 | B198: SHORTS TECH PIXEL | C198: TECH PIXEL SHORT | D198: 149.9 | E198: 33.311111
A199: I4012 | B199: COLETE FRESH NYLON | C199: NYLON FRESH VEST | D199: 227.9 | E199: 50.644444
A200: I4013 | B200: JAQUETA CORTA VENTO ULTRA LEVE | C200: ULTRALIGHT WINDBREAKER | D200: 249.9 | E200: 55.533333
... A412: P8117 | B412: LEGGING LIVE! | C412: LIVE! LEGGING | D412: 127.9 | E412: 28.422222
A413: 411
A414: 84325 | B414: GARRAFA HYDRA SPORTIF | C414: HYDRA SPORTIF BOTTLE | D414: 47.9 | E414: =D414/4.5 -> 10.644444
A415: 84445 | B415: BOLSA CROSS TRIP | C415: CROSS TRIP BAG | D415: 131.9 | E415: =D415/4.5 -> 29.311111
A416: 84447 | B416: BOLSA TRIP | C416: TRIP BAG | D416: 159.9 | E416: =D416/4.5 -> 35.533333
A417: 84448 | B417: MINI BAG ROAD | C417: ROAD MINI BAG | D417: 99.9 | E417: =D417/4.5 -> 22.2
A418: 84449 | B418: MOCHILA ROAD | C418: ROAD BACKPACK | D418: 218.9 | E418: =D418/4.5 -> 48.644444
A419: 84450 | B419: MOCHILA HIGH BREAK | C419: HIGH BREAK BACKPACK | D419: 209.9 | E419: =D419/4.5 -> 46.644444
A420: F2354 | B420: BOLSA MULTI HIT COLORS | C420: MULTI HIT COLORS BAG | D420: 134.9 | E420: =D420/4.5 -> 29.977778
A421: F2607 | B421: COQUETELEIRA PRO SPORT | C421: PRO SPORT COCKTAIL MAKER | D421: 89.9 | E421: =D421/4.5 -> 19.977778
A422: I2000 | B422: JAQUETA BOOST | C422: BOOST JACKET | D422: 262.9 | E422: =D422/4.5 -> 58.422222
A423: I2000 | B423: JAQUETA BOOST | C423: BOOST JACKET | D423: 262.9 | E423: =D423/4.5 -> 58.422222
A424: I2000 | B424: JAQUETA BOOST | C424: BOOST JACKET | D424: 262.9 | E424: =D424/4.5 -> 58.422222
A425: I2007 | B425: BAG DAYLIGHT | C425: DAYLIGHT BAG | D425: 159.9 | E425: =D425/4.5 -> 35.533333
A426: I2018 | B426: RAQUETE BEAT BT | C426: BEAT BT RACKET | D426: 634.9 | E426: =D426/4.5 -> 141.08889
A427: IF216 | B427: GARRAFA THERMO HOT&COLD | C427: THERMO HOT&COLD BOTTLE | D427: 87.9 | E427: =D427/4.5 -> 19.533333
A428: IP007 | B428: VISEIRA JET VISION | C428: JET VISION VISOR | D428: 81.9 | E428: =D428/4.5 -> 18.2
A429: IP007 | B429: VISEIRA JET VISION | C429: JET VISION VISOR | D429: 81.9 | E429: =D429/4.5 -> 18.2
A430: IP007 | B430: VISEIRA JET VISION | C430: JET VISION VISOR | D430: 81.9 | E430: =D430/4.5 -> 18.2
A431: IP008 | B431: VISEIRA SPEED RUN | C431: SPEED RUN VISOR | D431: 62.9 | E431: =D431/4.5 -> 13.977778
... A443: P9202 | B443: VISEIRA JET VISION | C443: JET VISION VISOR | D443: 76.9 | E443: =D443/4.5 -> 17.088889
A444: 61643 | C444: BLOUSE | D444: =E444*4.5 -> 204.9 | E444: 45.533333
A445: 61644 | C445: PANTS | D445: =E445*4.5 -> 181.9 | E445: 40.422222
A446: 61645 | C446: BLOUSE | D446: =E446*4.5 -> 159.9 | E446: 35.533333
A447: 61646 | C447: PANTS | D447: =E447*4.5 -> 204.9 | E447: 45.533333
A448: 61647 | C448: SEAMLESS CROPPED T-SHIRT | D448: =E448*4.5 -> 109.9 | E448: 24.422222
A449: 61648 | C449: T-SHIRT | D449: =E449*4.5 -> 81.9 | E449: 18.2
A450: 61649 | C450: SEAMLESS TANK TOP | D450: =E450*4.5 -> 68.9 | E450: 15.311111
A451: 61650 | C451: ACTIVE TOP | D451: =E451*4.5 -> 113.9 | E451: 25.311111
A452: 61651 | C452: ACTIVE LEGGING | D452: =E452*4.5 -> 145.9 | E452: 32.422222
A453: 61652 | C453: ACTIVE SHORT | D453: =E453*4.5 -> 113.9 | E453: 25.311111
A454: 61653 | C454: RACE PRO SPEED TOP | D454: =E454*4.5 -> 136.9 | E454: 30.422222
A455: 61654 | C455: RACE PRO SPEED SHORT | D455: =E455*4.5 -> 127.9 | E455: 28.422222
... A519: 61720 | C519: NYLON NET PANTS | D519: =E519*4.5 -> 172.9 | E519: 38.422222
A520: F2762 | C520: SEAMLESS EXPLORE TOP | D520: =E520*4.5 -> 89.9 | E520: 19.977778
A521: F2763 | C521: SEAMLESS EXPLORE LEGGING | D521: =E521*4.5 -> 136.9 | E521: 30.422222
A522: F2764 | C522: SEAMLESS JUMPSUIT SHORT | D522: =E522*4.5 -> 136.9 | E522: 30.422222
A523: F2765 | C523: V SEAMLESS TOP | D523: =E523*4.5 -> 89.9 | E523: 19.977778
A524: F2769 | C524: SEAMLESS LEGGING | D524: =E524*4.5 -> 113.9 | E524: 25.311111
A525: F2770 | C525: SEAMLESS SHORT | D525: =E525*4.5 -> 81.9 | E525: 18.2
A526: P0060 | C526: LIVE! SENSE PRO FIT SHORT | D526: =E526*4.5 -> 89.9 | E526: 19.977778
A527: P0063 | C527: LIVE! SENSE PRO CURVE TOP | D527: =E527*4.5 -> 89.9 | E527: 19.977778
A528: P0103 | C528: ALLURE NEO ADAPTIV TOP | D528: =E528*4.5 -> 109.9 | E528: 24.422222
A529: P0137 | C529: LIVE! SENSE PRO SKIRT | D529: =E529*4.5 -> 127.9 | E529: 28.422222
A530: P0138 | C530: V COMFORT T-SHIRT | D530: =E530*4.5 -> 81.9 | E530: 18.2
A531: P0141 | C531: ACTION SIDE T-SHIRT | D531: =E531*4.5 -> 89.9 | E531: 19.977778
...

Sheet Plan6
A1: NCM | B1: HS CODE | C1: Imposto | D1: Descrição
A2: 3923.30.00 | B2: 3923.30.00.90 | C2: 0.0404 | D2: shaker, squeeze
A3: 4202.22.10 | B3: 4202.22.15.00 | C3: 0.2708
A4: 4202.22.20 | B4: 4202.22.40.40 | C4: 0.0844 | D4: bolsa
A5: 4202.29.00 | B5: 4202.29.50.00 | C5: 0.0884 | D5: bolsa
A6: 4202.92.00 | B6: 4202.92.08.05 | C6: 0.0804
A7: 4202.92.00 | B7: 4202.92.08.07 | C7: 0.0804
A8: 4202.92.00 | B8: 4202.92.08.09 | C8: 0.0804
A9: 4202.99.00 | B9: 4202.99.50.00 | C9: 0.0884
A10: 4911.91.00 | B10: 4911.91.20.40 | C10: 0.0104 | D10: Catálogo, mini revista
A11: 6101.20.00 | B11: 6101.20.00.10 | C11: 0.1696
A12: 6101.30.00 | B12: 6101.30.20.10 | C12: 0.2924
A13: 6102.20.00 | B13: 6102.20.00.10 | C13: 0.1696 | D13: Casaco, kaftan
A14: 6102.30.00 | B14: 6102.30.20.10 | C14: 0.2924 | D14: jaqueta, casaco
A15: 6103.42.00 | B15: 6103.42.10.50 | C15: 0.1716 | D15: legging, shorts, fuso, bermuda, capri
A16: 6103.43.00 | B16: 6103.43.10.20 | C16: 0.1595 | D16: legging, shorts, fuso, bermuda, capri
A17: 6104.29.90 | B17: 6104.29.05.40 | C17: 0.0104
A18: 6104.42.00 | B18: 6104.42.00.10 | C18: 0.1256
A19: 6104.43.00 | B19: 6104.43.10.10 | C19: 0.1594 | D19: saída de praia
A20: 6104.44.00 | B20: 6104.44.20.10 | C20: 0.1594
A21: 6104.52.00 | B21: 6104.52.00.10 | C21: 0.0936
A22: 6104.53.00 | B22: 6104.53.10.00 | C22: 0.1594 | D22: shorts, vestido, saída de praia, saia shorts
A23: 6104.62.00 | B23: 6104.62.10.20 | C23: 0.1136
A24: 6104.63.00 | B24: 6104.63.10.20 | C24: 0.1595 | D24: legging, shorts, fuso, bermuda, capri
A25: 6105.20.00 | B25: 6105.20.10.00 | C25: 0.3305 | D25: blusa, regata
A26: 6106.10.00 | B26: 6106.10.00.10 | C26: 0.2076 | D26: blusa, regata
A27: 6106.20.00 | B27: 6106.20.10.10 | C27: 0.1594 | D27: Blusa, regata, casaco,
A28: 6109.10.00 | B28: 6109.10.00.70 | C28: 0.1756
A29: 6109.90.00 | B29: 6109.90.80.10 | C29: 0.1705 | D29: casual
A30: 6110.20.00 | B30: 6110.20.10.10 | C30: 0.0605
A31: 6110.20.00 | B31: 6110.20.10.20 | C31: 0.0606
A32: 6110.30.00 | B32: 6110.30.10.40 | C32: 0.0704 | D32: Colete
A33: 6112.12.00 | B33: 6112.12.00.20 | C33: 0.282 | D33: Shorts
A34: 6112.31.00 | B34: 6112.31.00.10 | C34: 0.2695 | D34: sunga
A35: 6112.41.00 | B35: 6112.41.00.10 | C35: 0.2595 | D35: top e tanga de biquini, maiô,
A36: 6114.20.00 | B36: 6114.20.00.10 | C36: 0.1186
A37: 6114.30.00 | B37: 6114.30.30.30 | C37: 0.1595 | D37: top, blusa
A38: 6115.95.00 | B38: 6115.95.90.00 | C38: 0.1456 | D38: meia
A39: 6116.93.00 | B39: 6116.93.08.00 | C39: 0.0384 | D39: luvas
A40: 6117.10.00 | B40: 6117.10.20.30 | C40: 12,34%%
A41: 6117.10.00 | B41: 6117.10.60.10 | C41: 0.1056 | D41: Skorts
A42: 6117.80.90 | B42: 6117.80.20.00 | C42: 0.0224 | D42: viseira, polaina, boné
A43: 6201.40.00 | B43: 6201.40.15.10 | C43: 0.2134
A44: 6202.13.00 | B44: 6202.13.10.00 | C44: 0.044
A45: 6202.40.00 | B45: 6202.40.15.10 | C45: 0.2127
A46: 6202.93.00 | B46: 6202.93.01.00 | C46: 0.044
A47: 6203.43.00 | B47: 6203.43.03.00 | C47: 0.0815 | D47: Shorts
A48: 6204.43.00 | B48: 6204.43.20.00 | C48: 0.0814 | D48: Kaftan, saída de praia
A49: 6204.44.00 | B49: 6204.44.30.10 | C49: 0.0954
A50: 6204.53.00 | B50: 6204.53.10.00 | C50: 0.149
A51: 6204.63.00 | B51: 6204.63.02.00 | C51: 0.0815
A52: 6204.69.00 | B52: 6204.69.01.10 | C52: 0.1465
A53: 6206.40.00 | B53: 6206.40.25.10 | C53: 0.1602
A54: 6206.40.00 | B54: 6206.40.30.10 | C54: 0.2795
A55: 6206.90.00 | B55: 6206.90.00.40 | C55: 0.0775
A56: 6211.43.00 | B56: 6211.43.05.10 | C56: 0.1705
A57: 6214.30.00 | B57: 6214.30.00.00 | C57: 0.0635 | D57: toalha de praia
A58: 6302.60.00 | B58: 6302.60.00.20 | C58: 0.1016 | D58: toalha fitness
A59: 6402.99.90 | B59: 6402.99.90.65 | C59: 0.2 | D59: chinelo de praia
A60: 6504.00.90 | B60: 6504.00.90.45 | C60: 0.0784
A61: 6505.00.12 | B61: 6505.00.04.10 | C61: 0.0104
A62: 6505.00.90 | B62: 6505.00.90.89 | C62: 0.0879
A63: 6506.99.00 | B63: 6506.99.60.00 | C63: 0.0954
A64: 7010.90.21 | B64: 7010.90.05.10 | C64: 0.0104
A65: 7323.93.00 | B65: 7323.93.00.45 | C65: 0.0304
A66: 7323.99.00 | B66: 7323.99.90.30 | C66: 0.0444
A67: 9617.00.10 | B67: 9617.00.10.00 | C67: 0.0824
A68: 6115.10.19 | B68: 6115.10.19.00
A69: 6106.90.00 | B69: 6106.90.30.40
A70: 4202.12.20 | B70: 4202.12.89.80
A71: 6206.30.00 | B71: 6206.30.30.41
A72: 6501.00.00 | B72: 6501.00.90.00
